Workbook

Sheet empty sheet
I1: DATE | J1: 46113
E3: RemiseBancaire(SAP) | I3: EXCEL
E4: Espèces | I4: ESPECES | K4: =E80+C14 -> 0
E5: Chèques | I5: CHEQUES | K5: =E15+E81 -> 0
E6: Monnaienondéposée | I6: CARTECREDIT | K6: =G15+E82 -> 0
I7: VIREMENT | K7: =SUM(E59:E64) -> 0
B8: CaisseEspèces | D8: Caissechèques | F8: CaisseCB
B9: Billetsde50 | D9: Client | E9: Montant | F9: Client | G9: Montant | I9: Dépenses:Essence,Divers | L9: Montant
B10: Billetsde20 | F10: Till
B11: Billetsde10 | F11: sancont
B12: Billetsde5
B13: Monnaie
B14: Total | C14: =SUM(C9:C13) -> 0
B15: Fonddecaisse | C15: 461 | D15: Total | E15: =SUM(E10:E14) -> 0 | F15: Total | G15: =SUM(G10:G14) -> 0 | I15: DifférenceFondCaisse
K16: Total | L16: =(SUM(L10:L15))*1 -> 0
A18: LIVRAISONS
A19: CODECLIENT | B19: PaiementsChèques | E19: Montant | F19: Banque | G19: Numero | H19: Remarques | L19: SAP
A38: CODECLIENT | B38: PaiementsEspèces | E38: Montant | F38: Remarques | L38: SAP
A48: CODECLIENT | B48: PaiementsCBSite | E48: Montant | F48: Remarques | L48: SAP
A53: CODECLIENT | B53: PaiementsCBTéléphone | E53: Montant | F53: Remarques | L53: SAP
C54: 802.36 | D54: cari versailles
C55: 675.28 | D55: cqfd
C56: 689.72 | D56: cqfd
C57: 340.26 | D57: new
A58: CODECLIENT | B58: Virements | E58: Montant | F58: Remarques | L58: SAP
A65: CODECLIENT | B65: Livraisonsnonpayées | E65: Montant | F65: Remarques | L65: SAP
B80: TOTALESPECES | E80: =SUM(E39:E47) -> 0
B81: TOTALCHEQUES | E81: =SUM(E20:E37) -> 0
B82: TOTALCBInternet&Phone | E82: =SUM(E49:E57) -> 0

Sheet 1
I1: DATE | J1: 46113
G2: no002804193330
E3: RemiseBancaire(SAP) | G3: no002804393210 | I3: EXCEL
E4: Espèces | F4: 9640 | G4: no002804243100 | I4: ESPECES | K4: =E82+C14 -> 9653.02
E5: Chèques | F5: 4711.78 | G5: no104711,78 | I5: CHEQUES | K5: =E15+E83 -> 4711.78
E6: Monnaienondéposée | F6: 13.02 | I6: CARTECREDIT | K6: =G15+E84 -> 16314.77
I7: VIREMENT | K7: =SUM(E58:E63) -> 0
B8: CaisseEspèces | D8: Caissechèques | F8: CaisseCB
B9: Billetsde50 | C9: 2300 | D9: Client | E9: Montant | F9: Client | G9: Montant | I9: Dépenses:Essence,Divers | L9: Montant
B10: Billetsde20 | C10: 3100 | D10: alishanrest | E10: 530.06 | F10: Till | G10: 16314.77 | I10: ahmedgasoil | L10: 80
B11: Billetsde10 | C11: 2300 | F11: sancont | I11: abubakaradvancemars2026 | L11: 600
B12: Billetsde5 | C12: 120
B13: Monnaie
B14: Total | C14: =SUM(C9:C13) -> 7820
B15: Fonddecaisse | C15: 713 | D15: Total | E15: =SUM(E10:E14) -> 530.06 | F15: Total | G15: =SUM(G10:G14) -> 16314.77 | I15: DifférenceFondCaisse | L15: =C15+[1]emptysheet!C15 -> #REF!
K16: Total | L16: =(SUM(L10:L15))*-1 -> #REF!
A18: LIVRAISONS
A19: CODECLIENT | B19: PaiementsChèques | E19: Montant | F19: Banque | G19: Numero | H19: Remarques | L19: SAP
A20: c4494 | B20: MCVDaumesnil | E20: 284.64 | F20: bred | G20: 8622364 | L20: ok
A21: c5362 | B21: ChezSUZETTE | E21: 300.51 | F21: lcl | G21: 2719859 | L21: ok
A22: c6616 | B22: SIRIUS | E22: 569.09 | F22: cic | G22: 4163035 | L22: ok
A23: c1756 | B23: davodistribution | E23: 918.2 | F23: lcl | G23: 4947306 | L23: ok
A24: c4168 | B24: restaurantk-chimaek | E24: 214.57 | F24: bnp | G24: 214.57 | L24: ok
A25: c5205 | B25: restaurantyoshiworld | E25: 278.15 | F25: ce | G25: 705 | L25: ok
A26: c4903 | B26: ROOSTERGRILLlam | E26: 311.96 | F26: ca | G26: 2265447 | L26: ok
A27: c4650 | B27: BREADSHOP | E27: 815.99 | F27: bp | G27: 2362 | L27: ok
A28: c7664 | B28: RestaurantCheezy | E28: 488.61 | F28: bnp | G28: 2693023 | L28: ok
A37: CODECLIENT | B37: PaiementsEspèces | E37: Montant | F37: Remarques | L37: SAP
A38: c6054 | B38: JadwigaWala | E38: 910.68 | L38: ok
A39: c3017 | B39: PFCARDINET(MATHIEUBoulangerie) | E39: 449.98 | L39: ok
A40: c4332 | B40: YBB | E40: 394.36 | L40: ok
B41: echangemonnais | E41: 78
A47: CODECLIENT | B47: PaiementsCBSite | E47: Montant | F47: Remarques | L47: SAP
A52: CODECLIENT | B52: PaiementsCBTéléphone | E52: Montant | F52: Remarques | L52: SAP
C53: 802.36 | D53: cari versailles
C54: 675.28 | D54: cqfd
C55: 689.72 | D55: cqfd
C56: 340.26 | D56: new
A57: CODECLIENT | B57: Virements | E57: Montant | F57: Remarques | L57: SAP
A64: CODECLIENT | B64: Livraisonsnonpayées | E64: Montant | F64: Remarques | L64: SAP
A65: c6727 | B65: SODIMACLuzzato | E65: 2270.4 | L65: ok
A66: c4523 | B66: NEHASTDENIS(chickenspot) | E66: 820.83 | L66: ok
A67: c5842 | B67: garbachaudlacourneuve | E67: 371.49 | L67: ok
A68: c6364 | B68: SARLLACREPESURMESURE | E68: 611.8 | L68: ok
A69: c5123 | B69: ErjiaKE | E69: 327.33 | L69: ok
A70: c6155 | B70: ZIGZAGCAFE | E70: 401.24 | L70: ok
A71: c6707 | B71: ShaziaBaig | E71: 795 | L71: ok
A72: c4368 | B72: RestaurantVanApril | E72: 296.34 | L72: ok
A73: c4231 | B73: Lesoleild'or | E73: 317.13 | L73: ok
A74: c6247 | C74: S&TCommerce | E74: 331.99 | L74: ok
A75: c5550 | C75: YohanSULTAN | E75: 421.77 | L75: ok
A76: c3585 | C76: SarlBurgerFactory2 | E76: 332.07 | L76: ok
A77: c4214 | B77: lafamilia | E77: 333.8 | L77: ok
A78: c7209 | B78: TENDERSBROTHERS | E78: 283.51 | L78: ok
B82: TOTALESPECES | E82: =SUM(E38:E46) -> 1833.02
B83: TOTALCHEQUES | E83: =SUM(E20:E36) -> 4181.72
B84: TOTALCBInternet&Phone | E84: =SUM(E48:E56) -> 0

Sheet 2
I1: DATE | J1: 46114
E3: RemiseBancaire(SAP) | G3: NO002804044130 | I3: EXCEL
E4: Espèces | F4: 7170 | G4: NO002803923040 | I4: ESPECES | K4: =E106+C14 -> 7173.88
E5: Chèques | F5: 9424.09 | G5: NO159424,09 | I5: CHEQUES | K5: =E15+E107 -> 9424.09
E6: Monnaienondéposée | F6: 3.88 | I6: CARTECREDIT | K6: =G15+E108 -> 41292.76
I7: VIREMENT | K7: =SUM(E74:E79) -> 0
B8: CaisseEspèces | D8: Caissechèques | F8: CaisseCB
B9: Billetsde50 | C9: 3300 | D9: Client | E9: Montant | F9: Client | G9: Montant | I9: Dépenses:Essence,Divers | L9: Montant
B10: Billetsde20 | C10: 1500 | D10: AUSUNDINE | E10: 391.29 | F10: Till | G10: 24011.5 | I10: amar | L10: 150
B11: Billetsde10 | C11: 690 | D11: OSPERSAN | E11: 1339.14 | F11: sancont | I11: samir | L11: 80
B12: Billetsde5 | C12: 140 | D12: ALISHANREST | E12: 283.35 | I12: skander | L12: 40
B13: Monnaie | I13: HOUCINE | L13: 80
B14: Total | C14: =SUM(C9:C13) -> 5630
B15: Fonddecaisse | C15: 536 | D15: Total | E15: =SUM(E10:E14) -> 2013.78 | F15: Total | G15: =SUM(G10:G14) -> 24011.5 | I15: DifférenceFondCaisse | L15: =C15-'1'!C15 -> -177
K16: Total | L16: =(SUM(L10:L15))*-1 -> -173
A18: LIVRAISONS
A19: CODECLIENT | B19: PaiementsChèques | E19: Montant | F19: Banque | G19: Numero | H19: Remarques | L19: SAP
A20: c6684 | B20: SOCIETEJH | E20: 373.97 | F20: sg | G20: 3840 | L20: ok
A21: c5420 | B21: Davidwarmuz | E21: 1003.9 | F21: lcl | G21: 2089630 | L21: ok
A22: c3757 | B22: SASTHON | E22: 338.35 | F22: lcl | G22: 9334211 | L22: OK
A23: C6651 | B23: ParissudEntreprise | E23: 505.37 | F23: BNP | G23: 7010120 | L23: OK
A24: c3476 | B24: VICTORIA168 | E24: 612.93 | F24: sg | G24: 297 | L24: ok
A25: c5238 | B25: Royalkebab | E25: 239.25 | F25: cm | G25: 5467728 | L25: ok
A26: c6124 | B26: A,M,C, | E26: 2339.63 | F26: lcl | G26: 3193128 | L26: ok
A27: c5499 | B27: LATIFAAFIF | E27: 410.47 | F27: sg | G27: 17 | L27: ok
A28: c541 | B28: SarlCdr | E28: 365.31 | F28: bp | G28: 251 | L28: ok
A29: c5435 | B29: Massis | E29: 489.13 | F29: sg | G29: 153 | L29: ok
A30: C5776 | B30: HaochiLI | E30: 282.65 | F30: BNP | G30: 878366 | L30: OK
A31: C6508 | B31: RannouchExpress | E31: 449.35 | F31: BNP | G31: 1681098 | L31: ok
A38: CODECLIENT | B38: PaiementsEspèces | E38: Montant | F38: Remarques | L38: SAP
A39: C6054 | B39: JadwigaWala | E39: 955.13 | L39: OK
A40: c5824 | B40: OBADAALMALLOUHI | E40: 328.18 | L40: ok
A41: c7030 | B41: OPUS | E41: 260.57 | L41: ok
A48: CODECLIENT | B48: PaiementsCBSite | E48: Montant | F48: Remarques | L48: SAP
A49: C4084 | B49: SOGEMAT | E49: 4233.82 | F49: EXTRA | L49: OK
A50: C5977 | C50: brandecision | E50: 3072.96 | L50: OK
A51: C7596 | C51: DEEPKITCHEN | E51: 2865.97 | L51: OK
A52: C6886 | C52: Lafourneedines | E52: 1290.22 | L52: OK
A53: C6735 | C53: Dolcedessert | E53: 1381.31 | L53: OK
A54: C7191 | C54: O'Tacos-MCLDISTRIBUTION | E54: 540.67 | L54: OK
A55: C7191 | B55: O'Tacos-MCLDISTRIBUTION | E55: 540.21 | L55: OK
A56: C7191 | C56: O'Tacos-MCLDISTRIBUTION | E56: 650.29 | L56: OK
A57: C6410 | C57: pitadinepitadine | E57: 2705.81 | L57: OK
A63: CODECLIENT | B63: PaiementsCBTéléphone | E63: Montant | F63: Remarques | L63: SAP
B64: CARESTURATIONEXTRA | C64: 802.36 | D64: cari versailles | F64: 3003.13 | L64: OK
C70: 675.28 | D70: cqfd
C71: 689.72 | D71: cqfd
C72: 340.26 | D72: new
A73: CODECLIENT | B73: Virements | E73: Montant | F73: Remarques | L73: SAP
A80: CODECLIENT | B80: Livraisonsnonpayées | E80: Montant | F80: Remarques | L80: SAP
A81: C7196 | B81: LIDISTRIBUTION | E81: 2006.45 | L81: ok
A82: c7634 | B82: WokFactory | E82: 1220.69 | L82: ok
A83: c3617 | B83: MNH | E83: 1885.71 | L83: ok
A84: c4357 | B84: BURGERISTE | E84: 414.55 | L84: ok
A85: C6018 | B85: MamiFood | E85: 2504.8 | L85: OK
A86: C7134 | B86: MEK'LA | E86: 306.37 | L86: OK
A87: c3127 | B87: moustacheetfils | E87: 728.16 | L87: ok
A88: c3938 | B88: SPICE'N'GRILL | E88: 721.94 | L88: ok
B89: halalcourse | E89: 161.69 | L89: ok
A90: c1259 | B90: SRSCHICKENSPOT(trembley) | E90: 649.4 | L90: ok
A91: c7675 | C91: TOKYORAMA(O'9POKE) | E91: 472.69 | L91: ok
A92: c3887 | C92: SARLVINVIN(BOJANAM) | E92: 348.06 | L92: ok
A93: c6555 | C93: AhmedBellahcene | E93: 1292 | L93: ok
A94: c7505 | C94: WAJIHHAMMOUD | E94: 307.75 | L94: ok
A95: c5729 | C95: JoeBurger | E95: 352.69 | L95: ok
A96: c2718 | C96: LILIANE&ILIANE | E96: 395.41 | L96: ok
A97: c7727 | C97: MohammedBodrulIslam | E97: 444.89 | L97: ok
C98: HALALCOURSE6274 | E98: 146.59 | H98: HALALCOURSE
A99: C6108 | C99: LEROCHER | E99: 316.89 | L99: OK
A100: C6380 | B100: lassaadbendaali | E100: 496.22 | L100: OK
A101: C6683 | C101: Chickenstate | E101: 2743.03 | L101: OK
A102: C2445 | C102: SUSHI&SNACKFOOD | E102: 477.88 | L102: OK
B106: TOTALESPECES | E106: =SUM(E39:E47) -> 1543.88
B107: TOTALCHEQUES | E107: =SUM(E20:E37) -> 7410.31
B108: TOTALCBInternet&Phone | E108: =SUM(E49:E72) -> 17281.26

Sheet 3
I1: DATE | J1: 46115
E3: RemiseBancaire(SAP) | G3: NO002803873485 | I3: EXCEL
E4: Espèces | F4: 10145 | G4: NO002803726660 | I4: ESPECES | K4: =E97+C14 -> 10149.46
E5: Chèques | F5: 2751.14 | G5: NO62751,14 | I5: CHEQUES | K5: =E15+E98 -> 2751.14
E6: Monnaienondéposée | F6: 4.5 | I6: CARTECREDIT | K6: =G15+E99 -> 37509.36
I7: VIREMENT | K7: =SUM(E73:E78) -> 0
B8: CaisseEspèces | D8: Caissechèques | F8: CaisseCB
B9: Billetsde50 | C9: 5150 | D9: Client | E9: Montant | F9: Client | G9: Montant | I9: Dépenses:Essence,Divers | L9: Montant
B10: Billetsde20 | C10: 1880 | D10: l'emeraude | E10: 466.53 | F10: Till | G10: 10834.72 | I10: skandergasoil | L10: 80
B11: Billetsde10 | C11: 2480 | D11: alishanrest | E11: 253.53 | F11: sancont | I11: SAMIRGASOIL | L11: 150
B12: Billetsde5 | D12: maxchicken | E12: 730.5 | I12: HOCINEACOMPTE | L12: 100
B13: Monnaie
B14: Total | C14: =SUM(C9:C13) -> 9510
B15: Fonddecaisse | D15: Total | E15: =SUM(E10:E14) -> 1450.56 | F15: Total | G15: =SUM(G10:G14) -> 10834.72 | I15: DifférenceFondCaisse | L15: =C15-'2'!C15 -> -536
K16: Total | L16: =(SUM(L10:L15))*-1 -> 206
A18: LIVRAISONS
A19: CODECLIENT | B19: PaiementsChèques | E19: Montant | F19: Banque | G19: Numero | H19: Remarques | L19: SAP
A20: C3215 | B20: AZAR | E20: 704.82 | F20: BP | G20: 222 | L20: OK
A21: c1936 | B21: LEPHENIX | E21: 297.5 | F21: ca | G21: 857179 | L21: ok
A22: c6940 | B22: mcvlavillette | E22: 298.26 | F22: sg | G22: 71 | L22: OK
A38: CODECLIENT | B38: PaiementsEspèces | E38: Montant | F38: Remarques | L38: SAP
A39: c5702 | B39: fahad | E39: 325 | L39: ok
A40: c7730 | B40: marvin | E40: 314.46 | L40: ok
A48: CODECLIENT | B48: PaiementsCBSite | E48: Montant | F48: Remarques | L48: SAP
A49: C6663 | B49: M,Comptoir | E49: 2705.81 | L49: OK
A50: C5977 | C50: brandecision | E50: 7000 | L50: OK
A51: C5977 | C51: brandecision | E51: 6500 | L51: OK
A52: C7196 | C52: LIDISTRIBUTION | E52: 2006.45 | L52: OK
A53: C7451 | C53: BigBangZone | E53: 2063.55 | L53: OK
A54: C6727 | C54: SODIMACLuzzato | E54: 2270.4 | L54: OK
A55: C6108 | C55: LEROCHER | E55: 285.86 | L55: OK
A56: C7604 | C56: maximestefanos | E56: 514.87 | L56: OK
A57: C5977 | C57: BRANDECISION | E57: 967.35 | L57: OK
A58: c7505 | C58: WAJIHHAMMOUD | E58: 307.75 | L58: OK
A59: C6555 | C59: AhmedBellahcene | E59: 1292 | L59: OK
A60: C2718 | C60: LILIANE&ILIANE | E60: 365.19 | L60: OK
A61: C2718 | C61: LILIANE&ILIANE | E61: 395.41 | L61: OK
A67: CODECLIENT | B67: PaiementsCBTéléphone | E67: Montant | F67: Remarques | L67: SAP
A68: c3218 | B68: EXTRAM,N,A | C68: 802.36 | D68: cari versailles | F68: 354.91 | L68: OK
C69: 675.28 | D69: cqfd
C70: 689.72 | D70: cqfd
C71: 340.26 | D71: new
A72: CODECLIENT | B72: Virements | E72: Montant | F72: Remarques | L72: SAP
A79: CODECLIENT | B79: Livraisonsnonpayées | E79: Montant | F79: Remarques | L79: SAP
A80: C5550 | B80: YohanSULTAN | E80: 398.03 | L80: OK
A81: C1113 | B81: CHICKENSPOTGENNEVILLIERS | E81: 1059.19 | L81: OK
A82: C6690 | B82: SASYLS | E82: 163.76 | L82: OK
A83: c7336 | B83: SCONE | E83: 958.11 | L83: ok
A84: c1513 | B84: EDENDI | E84: 4434.52 | L84: ok
A85: c2789 | B85: sasuberthe | E85: 440.82 | L85: OK
A86: c6767 | B86: sauce | E86: 420.63 | L86: OK
A87: c3485 | B87: carestauration | E87: 2597.04 | L87: OK
A88: c7518 | B88: osv | E88: 2417.12 | L88: OK
A89: c3127 | B89: moustacheetfils | E89: 1875.03 | L89: OK
A90: c6075 | B90: yasin | E90: 486.18 | L90: OK
A91: c6365 | B91: sarlcrepesurmesure | E91: 705.6 | L91: OK
... A94: c7499 | B94: thecorners | E94: 2623.64 | L94: OK
B97: TOTALESPECES | E97: =SUM(E39:E47) -> 639.46
B98: TOTALCHEQUES | E98: =SUM(E20:E37) -> 1300.58
B99: TOTALCBInternet&Phone | E99: =SUM(E49:E71) -> 26674.64

Sheet 4
G1: NO002803671670 | I1: DATE | J1: 46116
G2: NO002803323120
E3: RemiseBancaire(SAP) | G3: NO002803522180 | I3: EXCEL
E4: Espèces | F4: 13470 | G4: NO002803476500 | I4: ESPECES | K4: =E80+C14 -> 13470
E5: Chèques | F5: 1608.59 | G5: NO31608,59 | I5: CHEQUES | K5: =E15+E81 -> 1608.59
E6: Monnaienondéposée | I6: CARTECREDIT | K6: =G15+E82 -> 25778.66
I7: VIREMENT | K7: =SUM(E59:E64) -> 0
B8: CaisseEspèces | D8: Caissechèques | F8: CaisseCB
B9: Billetsde50 | C9: 6500 | D9: Client | E9: Montant | F9: Client | G9: Montant | I9: Dépenses:Essence,Divers | L9: Montant
B10: Billetsde20 | C10: 4220 | D10: BUFFETGARE | E10: 549.44 | F10: Till | G10: 25778.66 | I10: AHMEDGASOIL | L10: 80
B11: Billetsde10 | C11: 2540 | D11: BESTFALAFEL | E11: 531.42 | F11: sancont | I11: SKENDARGASOIL | L11: 80
B12: Billetsde5 | C12: 210 | D12: ALISHAN | E12: 527.73 | I12: SAMIRTRANSPORTER | L12: 250
B13: Monnaie
B14: Total | C14: =SUM(C9:C13) -> 13470
B15: Fonddecaisse | C15: 596 | D15: Total | E15: =SUM(E10:E14) -> 1608.59 | F15: Total | G15: =SUM(G10:G14) -> 25778.66 | I15: DifférenceFondCaisse | L15: =C15-'3'!C15 -> 596
K16: Total | L16: =(SUM(L10:L15))*-1 -> -1006
A18: LIVRAISONS
A19: CODECLIENT | B19: PaiementsChèques | E19: Montant | F19: Banque | G19: Numero | H19: Remarques | L19: SAP
A38: CODECLIENT | B38: PaiementsEspèces | E38: Montant | F38: Remarques | L38: SAP
A48: CODECLIENT | B48: PaiementsCBSite | E48: Montant | F48: Remarques | L48: SAP
A53: CODECLIENT | B53: PaiementsCBTéléphone | E53: Montant | F53: Remarques | L53: SAP
C54: 802.36 | D54: cari versailles
C55: 675.28 | D55: cqfd
C56: 689.72 | D56: cqfd
C57: 340.26 | D57: new
A58: CODECLIENT | B58: Virements | E58: Montant | F58: Remarques | L58: SAP
A65: CODECLIENT | B65: Livraisonsnonpayées | E65: Montant | F65: Remarques | L65: SAP
B80: TOTALESPECES | E80: =SUM(E39:E47) -> 0
B81: TOTALCHEQUES | E81: =SUM(E20:E37) -> 0
B82: TOTALCBInternet&Phone | E82: =SUM(E49:E57) -> 0

Sheet 5
I1: DATE | J1: 46117
E3: RemiseBancaire(SAP) | I3: EXCEL
E4: Espèces | I4: ESPECES | K4: =E80+C14 -> 0
E5: Chèques | I5: CHEQUES | K5: =E15+E81 -> 0
E6: Monnaienondéposée | I6: CARTECREDIT | K6: =G15+E82 -> 0
I7: VIREMENT | K7: =SUM(E59:E64) -> 0
B8: CaisseEspèces | D8: Caissechèques | F8: CaisseCB
B9: Billetsde50 | D9: Client | E9: Montant | F9: Client | G9: Montant | I9: Dépenses:Essence,Divers | L9: Montant
B10: Billetsde20 | F10: Till
B11: Billetsde10 | F11: sancont
B12: Billetsde5
B13: Monnaie
B14: Total | C14: =SUM(C9:C13) -> 0
B15: Fonddecaisse | D15: Total | E15: =SUM(E10:E14) -> 0 | F15: Total | G15: =SUM(G10:G14) -> 0 | I15: DifférenceFondCaisse | L15: =C15-'4'!C15 -> -596
K16: Total | L16: =(SUM(L10:L15))*-1 -> 596
A18: LIVRAISONS
A19: CODECLIENT | B19: PaiementsChèques | E19: Montant | F19: Banque | G19: Numero | H19: Remarques | L19: SAP
A38: CODECLIENT | B38: PaiementsEspèces | E38: Montant | F38: Remarques | L38: SAP
A48: CODECLIENT | B48: PaiementsCBSite | E48: Montant | F48: Remarques | L48: SAP
A53: CODECLIENT | B53: PaiementsCBTéléphone | E53: Montant | F53: Remarques | L53: SAP
C54: 802.36 | D54: cari versailles
C55: 675.28 | D55: cqfd
C56: 689.72 | D56: cqfd
C57: 340.26 | D57: new
A58: CODECLIENT | B58: Virements | E58: Montant | F58: Remarques | L58: SAP
A65: CODECLIENT | B65: Livraisonsnonpayées | E65: Montant | F65: Remarques | L65: SAP
B80: TOTALESPECES | E80: =SUM(E39:E47) -> 0
B81: TOTALCHEQUES | E81: =SUM(E20:E37) -> 0
B82: TOTALCBInternet&Phone | E82: =SUM(E49:E57) -> 0

Sheet 6
I1: DATE | J1: 46118
G2: NO002803271610
E3: RemiseBancaire(SAP) | G3: NO002803075110 | I3: EXCEL
E4: Espèces | F4: 10440 | G4: NO002803123720 | I4: ESPECES | K4: =E80+C14 -> 10440
E5: Chèques | F5: 1400.18 | G5: NO21400,18 | I5: CHEQUES | K5: =E15+E81 -> 1400.18
E6: Monnaienondéposée | I6: CARTECREDIT | K6: =G15+E82 -> 22371.77
I7: VIREMENT | K7: =SUM(E59:E64) -> 0
B8: CaisseEspèces | D8: Caissechèques | F8: CaisseCB
B9: Billetsde50 | C9: 3800 | D9: Client | E9: Montant | F9: Client | G9: Montant | I9: Dépenses:Essence,Divers | L9: Montant
B10: Billetsde20 | C10: 3580 | D10: ALISHANREST | E10: 545.99 | F10: Till | G10: 22371.77 | I10: HOCINEADBLU | L10: 32.5
B11: Billetsde10 | C11: 2920 | D11: AUSUNDINE | E11: 854.19 | F11: sancont | I11: AHMEDGASOIL | L11: 80
B12: Billetsde5 | C12: 140
B13: Monnaie
B14: Total | C14: =SUM(C9:C13) -> 10440
B15: Fonddecaisse | C15: 544 | D15: Total | E15: =SUM(E10:E14) -> 1400.18 | F15: Total | G15: =SUM(G10:G14) -> 22371.77 | I15: DifférenceFondCaisse | L15: =C15-'5'!C15 -> 544
K16: Total | L16: =(SUM(L10:L15))*-1 -> -656.5
A18: LIVRAISONS
A19: CODECLIENT | B19: PaiementsChèques | E19: Montant | F19: Banque | G19: Numero | H19: Remarques | L19: SAP
A38: CODECLIENT | B38: PaiementsEspèces | E38: Montant | F38: Remarques | L38: SAP
A48: CODECLIENT | B48: PaiementsCBSite | E48: Montant | F48: Remarques | L48: SAP
A53: CODECLIENT | B53: PaiementsCBTéléphone | E53: Montant | F53: Remarques | L53: SAP
C54: 802.36 | D54: cari versailles
C55: 675.28 | D55: cqfd
C56: 689.72 | D56: cqfd
C57: 340.26 | D57: new
A58: CODECLIENT | B58: Virements | E58: Montant | F58: Remarques | L58: SAP
A65: CODECLIENT | B65: Livraisonsnonpayées | E65: Montant | F65: Remarques | L65: SAP
B80: TOTALESPECES | E80: =SUM(E39:E47) -> 0
B81: TOTALCHEQUES | E81: =SUM(E20:E37) -> 0
B82: TOTALCBInternet&Phone | E82: =SUM(E49:E57) -> 0

Sheet 7
I1: DATE | J1: 46119
E3: RemiseBancaire(SAP) | G3: no002802805115 | I3: EXCEL
E4: Espèces | F4: 7265 | G4: no002802952150 | I4: ESPECES | K4: =E120+C14 -> 7276.35
E5: Chèques | F5: 13592.29 | G5: no1913592,29 | I5: CHEQUES | K5: =E15+E121 -> 13592.29
E6: Monnaienondéposée | F6: 11.35 | I6: CARTECREDIT | K6: =G15+E122 -> 27275.98
I7: VIREMENT | K7: =SUM(E58:E73) -> 18382.79
B8: CaisseEspèces | D8: Caissechèques | F8: CaisseCB
B9: Billetsde50 | C9: 2200 | D9: Client | E9: Montant | F9: Client | G9: Montant | I9: Dépenses:Essence,Divers | L9: Montant
B10: Billetsde20 | C10: 1820 | D10: 3afood | E10: 277.37 | F10: Till | G10: 26103.54 | I10: houcine | L10: 80
B11: Billetsde10 | C11: 2150 | D11: delta | E11: 3520.07 | F11: sancont
B12: Billetsde5 | C12: 30 | I12: aboubaker | L12: 85.85
B13: Monnaie | I13: samirgasoiletadblu | L13: 230
B14: Total | C14: =SUM(C9:C13) -> 6200 | I14: plumber | L14: 600
B15: Fonddecaisse | C15: 451 | D15: Total | E15: =SUM(E10:E14) -> 3797.44 | F15: Total | G15: =SUM(G10:G14) -> 26103.54 | I15: DifférenceFondCaisse | L15: =C15-'6'!C15 -> -93
K16: Total | L16: =(SUM(L10:L15))*-1 -> -902.85
A18: LIVRAISONS
A19: CODECLIENT | B19: PaiementsChèques | E19: Montant | F19: Banque | G19: Numero | H19: Remarques | L19: SAP
A20: c3237 | B20: LEMAGHREB | E20: 685.52 | F20: lcl | G20: 6786163 | L20: ok
A21: c7637 | B21: CHIKENFRENZY | E21: 2241.89 | F21: lcl | G21: 6155355 | L21: ok
A22: c1855 | B22: FRANPRIXSAVU | E22: 346.62 | F22: lcl | G22: 4142817 | L22: ok
A23: c4548 | B23: COTEPIGALLE | E23: 299.89 | F23: bp | G23: 493 | L23: ok
A24: c1842 | B24: GUOCHENG | E24: 573.51 | F24: ca | G24: 2916564 | L24: ok
A25: c4204 | B25: Kashmirexpress | E25: 302.95 | F25: lcl | G25: 2722680 | L25: ok
A26: c5161 | B26: K-CHI | E26: 339 | F26: bnp | G26: 9427205 | L26: ok
A27: c3476 | B27: VICTORIA168 | E27: 656.13 | F27: sg | G27: 298 | L27: ok
A28: c5707 | B28: BibimElancourt | E28: 425.53 | F28: ca | G28: 473 | L28: ok
A29: c1428 | B29: NOUJOUM | E29: 246.1 | F29: ca | G29: 2032 | L29: ok
A30: c2987 | B30: boulangerielespoètes | E30: 488.65 | F30: caissedepargne | G30: 697 | L30: ok
A31: c6940 | B31: MCVLAVILLETTE | E31: 375.16 | F31: sg | G31: 72 | L31: ok
... A36: c1376 | B36: DELICEHOUSESUSHIWASABI | E36: 368.32 | F36: ce | G36: 9978481 | L36: ok
A37: CODECLIENT | B37: PaiementsEspèces | E37: Montant | F37: Remarques | L37: SAP
B38: retourhoucine | E38: 12.5 | F38: gasoil
A39: c2431 | B39: ARGENSONETSEPTARPENTS | E39: 160 | L39: ok
A40: c2414 | B40: LAROTISSERIE | E40: 393.37 | L40: ok
A41: c5276 | B41: Silan | E41: 352.26 | L41: ok
B42: CookandFood | E42: 158.22 | F42: extra | L42: ok
A47: CODECLIENT | B47: PaiementsCBSite | E47: Montant | F47: Remarques | L47: SAP
A48: c3051 | B48: premierfood | E48: 228.17 | L48: ok
B49: stephanedelalande | E49: 348.06 | F49: 345.87 | G49: 2.19 | H49: paypal+cash | L49: ok
A50: c7738 | B50: ISIA | E50: 596.21 | F50: extra | L50: ok
A52: CODECLIENT | B52: PaiementsCBTéléphone | E52: Montant | F52: Remarques | L52: SAP
C53: 802.36 | D53: cari versailles
C54: 675.28 | D54: cqfd
C55: 689.72 | D55: cqfd
C56: 340.26 | D56: new
A57: CODECLIENT | B57: Virements | E57: Montant | F57: Remarques | L57: SAP
B58: QFDBEAUVAIS | E58: 2442.35 | L58: ok
B59: LEIFOOD | E59: 506.7 | L59: ok
B60: OVENFOOD | E60: 2568.61 | L60: ok
B61: S,A,S,HETNMARKET | E61: 375.85 | L61: ok
B62: S,A,R,L,CASAMIA | E62: 513.13 | L62: ok
B63: MARKETDEPOTPSB | E63: 1053.95 | L63: ok
B64: OVENFOOD | E64: 1396.48 | L64: ok
B65: W,TFOOD | E65: 432.71 | L65: ok
B66: BURGER45STREET | E66: 394 | L66: ok
B67: EPICERIEALIMENTAIRE | E67: 954.62 | L67: ok
B68: MMECHOUITERILHAM | E68: 3525.26 | L68: ok
B69: OVENFOOD | E69: 2126.45 | L69: ok
... B73: CHERRYGARDENS | E73: 239.83 | L73: ok
A74: CODECLIENT | B74: Livraisonsnonpayées | E74: Montant | F74: Remarques | L74: SAP
A75: c7675 | B75: TOKYORAMA(O'9POKE) | E75: 204.52 | L75: ok
A76: c6244 | B76: CHIKINCERGY | E76: 738.39 | L76: ok
A77: c5873 | B77: Luna | E77: 303.67 | L77: ok
A78: c7745 | B78: DavidRobillard | E78: 335.14 | L78: ok
A79: c6052 | B79: LesTurbines | E79: 289.86 | L79: ok
A80: c1886 | B80: LECHINOISGOURMET | E80: 438.46 | L80: ok
A81: c4379 | B81: SUKISOBA | E81: 380.55 | L81: ok
A82: c6690 | B82: SASYLS | E82: 365.76 | L82: ok
A83: c1465 | B83: DELICEDEBEYROUTHIHLIBAN | E83: 615.52 | L83: ok
A84: c2445 | C84: SUSHI&SNACKFOOD | E84: 414.56 | L84: ok
A85: c6683 | C85: Chickenstate | E85: 1601.67 | L85: ok
A86: c5923 | C86: ChezPAUL | E86: 637.29 | L86: ok
A87: c5923 | C87: ChezPAUL | E87: 771.02 | L87: ok
A88: c7634 | C88: WokFactory | E88: 1026.44 | L88: ok
A89: c7478 | C89: KFEKaptainFry | E89: 1853.22 | L89: ok
A90: c6018 | C90: MamiFood | E90: 2639.81 | L90: ok
A91: c6395 | C91: THEKITCHENEATMEATPARIS | E91: 358.4 | L91: ok
A92: c5083 | C92: Chulavista | E92: 300.66 | L92: ok
A93: c6690 | C93: SASYLS | E93: 115.94 | L93: ok
A94: c4368 | C94: RestaurantVanApril | E94: 428.67 | L94: ok
A95: c5863 | C95: KINGFOOD | E95: 333.64 | L95: ok
A96: c2886 | B96: NEHAAUBERVILLER(chickenspot) | E96: 595.99 | L96: ok
A97: c2729 | C97: SANA | E97: 1201.27 | L97: ok
A98: c1259 | C98: SRSCHICKENSPOT(trembley) | E98: 481.24 | L98: ok
A99: c7396 | C99: LESSAVEURSDEGRETZ | E99: 388.44 | L99: ok
A100: c7713 | C100: ArnaudLlinares | E100: 983.92 | L100: ok
A101: c3141 | C101: DIPSAMATIC | E101: 11177.41 | L101: ok
A102: c3455 | C102: THEBEANPROJECTPARIS | E102: 216.67 | L102: ok
A103: c6471 | C103: MozzafiatoParis | E103: 300.16 | L103: ok
A104: c7604 | C104: maximestefanos | E104: 782.04 | L104: ok
A105: c6918 | C105: MEOKJA | E105: 177.08 | L105: ok
A106: c7737 | C106: SARLPESNEL | E106: 966.56 | L106: ok
A107: c3938 | C107: SPICE'N'GRILLRestaurant | E107: 650.09 | L107: ok
A108: c7164 | C108: IlyesElMorabit | E108: 19/12/190004:19:12 | L108: ok
A109: c4800 | C109: SHAMEEM(Chickenspot) | E109: 949.47 | L109: ok
A110: c6658 | C110: SASBoulangeriemaisondessaveurs | E110: 838.5 | L110: ok
A111: c6551 | C111: jadalrayes | E111: 899.02 | L111: ok
A112: c2445 | C112: SUSHI&SNACKFOOD | E112: 365.53 | L112: ok
A113: c5850 | C113: CRAZYPIMENT2 | E113: 357.88 | L113: ok
A114: c7336 | C114: SCONE | E114: 574.29 | L114: ok
...

Sheet 8
I1: DATE | J1: 46120
G2: no002802554130
E3: RemiseBancaire(SAP) | G3: no002802754215 | I3: EXCEL
E4: Espèces | F4: 10205 | G4: no002802601860 | I4: ESPECES | K4: =E82+C14 -> 10206.6
E5: Chèques | F5: 4772.85 | G5: no94772,85 | I5: CHEQUES | K5: =E15+E83 -> 4772.85
E6: Monnaienondéposée | F6: 1.7 | I6: CARTECREDIT | K6: =G15+E84 -> 24660.95
I7: VIREMENT | K7: =SUM(E59:E64) -> 0
B8: CaisseEspèces | D8: Caissechèques | F8: CaisseCB
B9: Billetsde50 | C9: 3250 | D9: Client | E9: Montant | F9: Client | G9: Montant | I9: Dépenses:Essence,Divers | L9: Montant
B10: Billetsde20 | C10: 2640 | D10: alishanrest | E10: 492.33 | F10: Till | G10: 24660.95 | I10: SAMIRGASOIL | L10: 300
B11: Billetsde10 | C11: 2600 | D11: maxchic | E11: 743.17 | F11: sancont | I11: AHMEDGASOIL | L11: 80
B12: Billetsde5 | C12: 225 | I12: SKANDERGASOIL(RENDU) | L12: 80
B13: Monnaie | I13: rembursmentclient | L13: 34.8
B14: Total | C14: =SUM(C9:C13) -> 8715 | I14: ahmedpeage | L14: 3.8
B15: Fonddecaisse | C15: 366 | D15: Total | E15: =SUM(E10:E14) -> 1235.5 | F15: Total | G15: =SUM(G10:G14) -> 24660.95 | I15: DifférenceFondCaisse | L15: =C15-'7'!C15 -> -85
K16: Total | L16: =(SUM(L10:L15))*-1 -> -413.6
A18: LIVRAISONS
A19: CODECLIENT | B19: PaiementsChèques | E19: Montant | F19: Banque | G19: Numero | H19: Remarques | L19: SAP
A20: C1373 | B20: SARLWANOBI | E20: 291.91 | F20: SG | G20: 3597 | L20: OK
A21: C5144 | B21: MCVFAIDHERBE | E21: 465.96 | F21: BRED | G21: 7051121 | L21: OK
A22: C5144 | B22: MCVFAIDHERBE | E22: 467.46 | F22: BRED | G22: 7051122 | H22: ANCIENPAIEMENT | L22: OK
A23: C1222 | B23: RELAISD'OR | E23: 461.41 | F23: CIC | G23: 2569200 | L23: OK
A24: C5316 | B24: PIZZERIAVIVALDI | E24: 363.45 | F24: CIC | G24: 3684538 | L24: OK
A25: C6212 | B25: EURLHE | E25: 549.34 | F25: CIC | G25: 8309673 | L25: OK
A26: C4602 | B26: CHAMAS | E26: 937.82 | F26: CIC | G26: 3885361 | L26: OK
A38: CODECLIENT | B38: PaiementsEspèces | E38: Montant | F38: Remarques | L38: SAP
A39: C7735 | B39: RAPIDEFOOD | E39: 450.7 | L39: OK
A40: C9999 | B40: VCCROUSTYFAMILY | E40: 960.9 | L40: OK
B41: RETOURGASOILSKANDER | E41: 80
A48: CODECLIENT | B48: PaiementsCBSite | E48: Montant | F48: Remarques | L48: SAP
A53: CODECLIENT | B53: PaiementsCBTéléphone | E53: Montant | F53: Remarques | L53: SAP
C54: 802.36 | D54: cari versailles
C55: 675.28 | D55: cqfd
C56: 689.72 | D56: cqfd
C57: 340.26 | D57: new
A58: CODECLIENT | B58: Virements | E58: Montant | F58: Remarques | L58: SAP
A65: CODECLIENT | B65: Livraisonsnonpayées | E65: Montant | F65: Remarques | L65: SAP
A66: C5842 | B66: GARBACHAUD | E66: 399.47 | L66: OK
A67: C1971 | B67: ESCOMPANY | E67: 520.62 | L67: OK
A68: C5877 | B68: ANOUAR | E68: 968.16 | L68: OK
A69: C7100 | B69: LEKINKS | E69: 2506.23 | L69: OK
A70: C1838 | B70: BETAFOOD | E70: 404.32 | L70: OK
A71: HC | B71: N,6277 | E71: 159.6
A72: C6973 | B72: JKDISTRIBUTION | E72: 11671.32 | F72: SURPLACE | L72: OK
A73: C6294 | B73: CROUSTYFAMILY | E73: 1888.85 | L73: OK
A74: C7191 | B74: CHARLES | E74: 695.91 | L74: OK
A75: C4207 | B75: JULIENNE | E75: 358.06 | L75: OK
A76: C7336 | B76: SCONE | E76: 492.99 | L76: OK
A77: C7692 | B77: SANDRINE | E77: 429.57 | L77: OK
A78: C6459 | B78: FATIMA | E78: 436.46 | L78: OK
A79: C4368 | B79: VANAPRIL | E79: 464.84 | L79: OK
A80: C6018 | B80: MAMIFOOD | E80: 2523.35 | L80: OK
B82: TOTALESPECES | E82: =SUM(E39:E47) -> 1491.6
B83: TOTALCHEQUES | E83: =SUM(E20:E37) -> 3537.35
B84: TOTALCBInternet&Phone | E84: =SUM(E49:E57) -> 0

Sheet 9
I1: DATE | J1: 46121
E3: RemiseBancaire(SAP) | G3: no002802354345 | I3: EXCEL
E4: Espèces | F4: 9085 | G4: no002802404740 | I4: ESPECES | K4: =E90+C14 -> 9089.25
E5: Chèques | F5: 3332.54 | G5: no93332,54 | I5: CHEQUES | K5: =E15+E91 -> 3332.54
E6: Monnaienondéposée | F6: 4.25 | I6: CARTECREDIT | K6: =G15+E92 -> 14803.5
I7: VIREMENT | K7: =SUM(E59:E64) -> 0
B8: CaisseEspèces | D8: Caissechèques | F8: CaisseCB
B9: Billetsde50 | C9: 2900 | D9: Client | E9: Montant | F9: Client | G9: Montant | I9: Dépenses:Essence,Divers | L9: Montant
B10: Billetsde20 | C10: 2020 | D10: alishan | E10: 233.74 | F10: Till | G10: 18255.95 | I10: skandergasoil | L10: 80
B11: Billetsde10 | C11: 2320 | D11: ausundine | E11: 357.04 | F11: sancont | I11: samirgasoil | L11: 70
B12: Billetsde5 | C12: 125 | F12: sobicashextra | G12: 2700
B13: Monnaie | F13: sobicashextra | G13: 752.45
B14: Total | C14: =SUM(C9:C13) -> 7365
B15: Fonddecaisse | C15: 488 | D15: Total | E15: =SUM(E10:E14) -> 590.78 | F15: Total | G15: =SUM(G10-G12-G13)+G11 -> 14803.5 | I15: DifférenceFondCaisse | L15: =C15-'8'!C15 -> 122
K16: Total | L16: =(SUM(L10:L15))*-1 -> -272
A18: LIVRAISONS
A19: CODECLIENT | B19: PaiementsChèques | E19: Montant | F19: Banque | G19: Numero | H19: Remarques | L19: SAP
A20: c6508 | B20: RannouchExpress | E20: 506.27 | F20: bnp | G20: 1681099 | L20: ok
A21: c7142 | B21: CHEZMIMI | E21: 301.31 | F21: bnp | G21: 7642072 | L21: ok
A22: c4215 | B22: BOULANGERIECAJAN | E22: 598.02 | F22: bp | G22: 113 | L22: ok
A23: c7619 | B23: BrahimChammakhi | E23: 324.13 | F23: lcl | G23: 2441412 | L23: ok
A24: c5355 | B24: RedhaDJAMA | E24: 294.79 | F24: lcl | G24: 654799 | L24: ok
B25: SarlCdr | E25: 415.78 | F25: bp | G25: 255 | L25: ok
A26: c1526 | B26: SUSHIYAKI | E26: 301.46 | F26: cic | G26: 1208973
A38: CODECLIENT | B38: PaiementsEspèces | E38: Montant | F38: Remarques | L38: SAP
A39: c6114 | B39: sobicash | E39: 1000 | F39: enlevementsurplace | L39: ok
A40: c3017 | B40: PFCARDINET(MATHIEUBoulangerie) | E40: 403.1 | L40: ok
A41: c7753 | B41: BENAYADMOHAMED | E41: 321.15 | L41: ok
A48: CODECLIENT | B48: PaiementsCBSite | E48: Montant | F48: Remarques | L48: SAP
A53: CODECLIENT | B53: PaiementsCBTéléphone | E53: Montant | F53: Remarques | L53: SAP
C54: 802.36 | D54: cari versailles
C55: 675.28 | D55: cqfd
C56: 689.72 | D56: cqfd
C57: 340.26 | D57: new
A58: CODECLIENT | B58: Virements | E58: Montant | F58: Remarques | L58: SAP
A65: CODECLIENT | B65: Livraisonsnonpayées | E65: Montant | F65: Remarques | L65: SAP
A66: c5431 | B66: DreamFactory | E66: 303.08 | L66: ok
A67: c6004 | B67: NEWSOULFOOD | E67: 443.1 | L67: ok
A68: c6367 | B68: SARLLACREPESURMESURE | E68: 1121.67 | L68: ok
A69: c3127 | B69: moustacheetfils | E69: 1760.97 | L69: ok
A70: c2108 | B70: AR-Chickenspot | E70: 737.88 | L70: ok
A71: c6802 | B71: TorabMaroof | E71: 880.59 | L71: ok
A72: c6000 | B72: AYROEV | E72: 1243.36 | L72: ok
A73: c6948 | C73: AntoinePeresse | E73: 376.92 | L73: ok
A74: c3458 | C74: SarlSAMIE(Chickenspot) | E74: 686 | L74: ok
C75: halalcourse6278 | E75: 124.2 | H75: halalcourse
A76: c1732 | C76: sarlfriedchicken | E76: 358.27 | L76: ok
A77: c7621 | C77: COVASERVICES | E77: 316.44 | L77: ok
A78: c4946 | C78: BKGroupe | E78: 1615.33 | L78: ok
A79: c7604 | B79: maximestefanos | E79: 617.21 | L79: ok
A80: c6683 | B80: Chickenstate | E80: 1586.91 | L80: ok
A81: c6366 | C81: SARLLACREPESURMESURE | E81: 1055.99 | L81: ok
A82: c6769 | C82: LACREMEDEPARISEntreprise | E82: 3118.32 | L82: ok
A83: c7754 | C83: LECARIBEENRESTAURENT | E83: 3797.05 | L83: ok
B90: TOTALESPECES | E90: =SUM(E39:E47) -> 1724.25
B91: TOTALCHEQUES | E91: =SUM(E20:E37) -> 2741.76
B92: TOTALCBInternet&Phone | E92: =SUM(E49:E57) -> 0

Sheet 11
I1: DATE | J1: 46123
G2: no002801986490
E3: RemiseBancaire(SAP) | G3: no002801832000 | I3: EXCEL
E4: Espèces | F4: 13690 | G4: no002802005200 | I4: ESPECES | K4: =E80+C14 -> 13690
E5: Chèques | F5: 1582.95 | G5: no31582,95 | I5: CHEQUES | K5: =E15+E81 -> 1582.95
E6: Monnaienondéposée | I6: CARTECREDIT | K6: =G15+E82 -> 22365.06
I7: VIREMENT | K7: =SUM(E59:E64) -> 0
B8: CaisseEspèces | D8: Caissechèques | F8: CaisseCB
B9: Billetsde50 | C9: 5000 | D9: Client | E9: Montant | F9: Client | G9: Montant | I9: Dépenses:Essence,Divers | L9: Montant
B10: Billetsde20 | C10: 5200 | D10: buffetgare | E10: 744.8 | F10: Till | G10: 22365.06 | I10: skandergasoil | L10: 80
B11: Billetsde10 | C11: 3490 | D11: lbf | E11: 339.88 | F11: sancont | I11: skandersamdi | L11: 260
B12: Billetsde5 | D12: alishanrest | E12: 498.27 | I12: houcinegasoil | L12: 80
B13: Monnaie | I13: ahmedgasoil | L13: 80
B14: Total | C14: =SUM(C9:C13) -> 13690
B15: Fonddecaisse | C15: 412 | D15: Total | E15: =SUM(E10:E14) -> 1582.95 | F15: Total | G15: =SUM(G10:G14) -> 22365.06 | I15: DifférenceFondCaisse | L15: =C15-'10'!C15 -> -28
K16: Total | L16: =(SUM(L10:L15))*-1 -> -472
A18: LIVRAISONS
A19: CODECLIENT | B19: PaiementsChèques | E19: Montant | F19: Banque | G19: Numero | H19: Remarques | L19: SAP
A38: CODECLIENT | B38: PaiementsEspèces | E38: Montant | F38: Remarques | L38: SAP
A48: CODECLIENT | B48: PaiementsCBSite | E48: Montant | F48: Remarques | L48: SAP
A53: CODECLIENT | B53: PaiementsCBTéléphone | E53: Montant | F53: Remarques | L53: SAP
C54: 802.36 | D54: cari versailles
C55: 675.28 | D55: cqfd
C56: 689.72 | D56: cqfd
C57: 340.26 | D57: new
A58: CODECLIENT | B58: Virements | E58: Montant | F58: Remarques | L58: SAP
A65: CODECLIENT | B65: Livraisonsnonpayées | E65: Montant | F65: Remarques | L65: SAP
B80: TOTALESPECES | E80: =SUM(E39:E47) -> 0
B81: TOTALCHEQUES | E81: =SUM(E20:E37) -> 0
B82: TOTALCBInternet&Phone | E82: =SUM(E49:E57) -> 0

Sheet 10
I1: DATE | J1: 46122
E3: RemiseBancaire(SAP) | G3: no002802204440 | I3: EXCEL
E4: Espèces | F4: 6710 | G4: no002802152270 | I4: ESPECES | K4: =E103+C14 -> 6717.7
E5: Chèques | F5: 4120.46 | G5: no106723,37 | I5: CHEQUES | K5: =E15+E104 -> 6723.37
E6: Monnaienondéposée | F6: 7.7 | I6: CARTECREDIT | K6: =G15+E105 -> 26138.03
I7: VIREMENT | K7: =SUM(E68:E73) -> 0
B8: CaisseEspèces | D8: Caissechèques | F8: CaisseCB
B9: Billetsde50 | C9: 2000 | D9: Client | E9: Montant | F9: Client | G9: Montant | I9: Dépenses:Essence,Divers | L9: Montant
B10: Billetsde20 | C10: 1940 | D10: alishanrest | E10: 309.49 | F10: Till | G10: 15955.55 | I10: ahmed | L10: 80
B11: Billetsde10 | C11: 2270 | F11: sancont | I11: samir | L11: 80
B12: Billetsde5 | C12: 30 | I12: skander | L12: 80
B13: Monnaie
B14: Total | C14: =SUM(C9:C13) -> 6240
B15: Fonddecaisse | C15: 440 | D15: Total | E15: =SUM(E10:E14) -> 309.49 | F15: Total | G15: =SUM(G10:G14) -> 15955.55 | I15: DifférenceFondCaisse | L15: =C15-'9'!C15 -> -48
K16: Total | L16: =(SUM(L10:L15))*-1 -> -192
A18: LIVRAISONS
A19: CODECLIENT | B19: PaiementsChèques | E19: Montant | F19: Banque | G19: Numero | H19: Remarques | L19: SAP
B20: HOTPIZZA77 | E20: 347 | F20: CIC | G20: 6361484 | L20: OK
A21: c7615 | B21: zaheralkhubi | E21: 575.61 | F21: lcl | G21: 3260692 | L21: ok
A22: c5052 | B22: RESTOBEYROUTH | E22: 356.36 | F22: sg | G22: 2000424 | L22: ok
A23: c6707 | B23: ShaziaBaig | E23: 642.68 | F23: bnp | G23: 2650137 | L23: ok
A24: c5004 | B24: RobertAsseraf | E24: 639.15 | F24: sg | G24: 891 | L24: ok
A25: c3757 | B25: SASTHON | E25: 280.39 | F25: lcl | G25: 9334224 | L25: ok
A26: c3476 | B26: VICTORIA168 | E26: 689.38 | F26: sg | G26: 299 | L26: ok
A27: c2938 | B27: MCVDumas | E27: 280.4 | F27: bred | G27: 8738421 | L27: ok
B28: EXTRASARLSTEABRAJ | E28: 2602.91
A38: CODECLIENT | B38: PaiementsEspèces | E38: Montant | F38: Remarques | L38: SAP
B39: skander | E39: 80 | F39: retourgasoil
A40: c3888 | B40: CHICKENHOTETPIZZA | E40: 3.72 | F40: extra | L40: ok
A41: c5702 | B41: FahadMuhammad | E41: 393.98 | L41: ok
A48: CODECLIENT | B48: PaiementsCBSite | E48: Montant | F48: Remarques | L48: SAP
A53: CODECLIENT | B53: PaiementsCBTéléphone | E53: Montant | F53: Remarques | L53: SAP
A54: C7396 | B54: LESSAVEURSDEGRETZ | C54: 802.36 | D54: cari versailles | E54: 388.44 | L54: OK
A55: C6534 | C55: DEDAMASABEYROUTH | E55: 347.01 | L55: OK
A56: C6446 | C56: LEBNEN | E56: 300 | L56: OK
A57: c7737 | C57: SARLPESNEL | E57: 966.56 | L57: ok
A58: C4202 | C58: LAFRAICHEUR | E58: 3338.67 | L58: OK
A59: C5716 | C59: GIEMF | E59: 4288.15 | L59: OK
A60: C7604 | C60: maximestefanos | E60: 553.65 | L60: OK
C64: 675.28 | D64: cqfd
C65: 689.72 | D65: cqfd
C66: 340.26 | D66: new
A67: CODECLIENT | B67: Virements | E67: Montant | F67: Remarques | L67: SAP
A74: CODECLIENT | B74: Livraisonsnonpayées | E74: Montant | F74: Remarques | L74: SAP
A75: c2789 | B75: SASUBERTHE | E75: 413.93 | L75: ok
A76: c2718 | B76: LILIANE&ILIANE | E76: 380.15 | L76: ok
A77: c6364 | B77: SARLLACREPESURMESURE | E77: 393.78 | L77: ok
A78: c2445 | B78: SUSHI&SNACKFOOD | E78: 476.17 | L78: ok
A79: c2152 | B79: LESTROISAMIS | E79: 441.81 | L79: ok
A80: c1681 | B80: ALAFOLIEPARIS | E80: 483.94 | L80: ok
A81: c4368 | B81: RestaurantVanApril | E81: 155.22 | F81: facture02/04 | L81: OK
A82: c6569 | B82: O'CroustiTime | E82: 415.21 | L82: ok
A83: c7336 | B83: SCONE | E83: 942.07 | L83: ok
A84: c7488 | B84: W,TFOOD | E84: 438.6 | L84: ok
A85: c4368 | C85: RestaurantVanApril | E85: 323.01 | L85: ok
A86: c3127 | C86: moustacheetfils | E86: 1435.66 | L86: ok
A87: c1832 | C87: SARLLE59 | E87: 1675.91 | L87: ok
A88: c7191 | C88: O'Tacos-MCLDISTRIBUTION | E88: 763.89 | L88: ok
A89: c7758 | C89: LaurentBourdindiXlo | E89: 325.89 | L89: ok
A90: c7675 | C90: TOKYORAMA(O'9POKE) | E90: 404.74 | L90: ok
A91: c6018 | C91: MamiFood | E91: 2540 | L91: ok
A92: c3585 | C92: SarlBurgerFactory2 | E92: 315.55 | L92: ok
A93: c7741 | C93: O'GARDEN | E93: 936.42 | L93: ok
A94: c5848 | C94: GuillaumeCourtois | E94: 350.37 | L94: ok
A95: c7505 | C95: WAJIHHAMMOUD | E95: 308.2 | L95: ok
A96: c6767 | C96: SAUCE | E96: 404.81 | L96: ok
A97: c6194 | C97: assilak | E97: 1113.62 | L97: ok
B103: TOTALESPECES | E103: =SUM(E39:E47) -> 477.7
B104: TOTALCHEQUES | E104: =SUM(E20:E37) -> 6413.88
B105: TOTALCBInternet&Phone | E105: =SUM(E49:E66) -> 10182.48

Sheet 13
I1: DATE | J1: 46125
E3: RemiseBancaire(SAP) | G3: no002797563480 | I3: EXCEL
E4: Espèces | F4: 8140 | G4: no00280784660 | I4: ESPECES | K4: =E233+C14 -> 8149.22
E5: Chèques | F5: 5447.35 | G5: no135447,35 | I5: CHEQUES | K5: =E15+E234 -> 5447.35
E6: Monnaienondéposée | F6: 9.42 | I6: CARTECREDIT | K6: =G15+E235 -> 19299.85
I7: VIREMENT | K7: =SUM(E59:E209) -> 293540.43
B8: CaisseEspèces | D8: Caissechèques | F8: CaisseCB
B9: Billetsde50 | C9: 2750 | D9: Client | E9: Montant | F9: Client | G9: Montant | I9: Dépenses:Essence,Divers | L9: Montant
B10: Billetsde20 | C10: 2020 | D10: ausundine | E10: 821.3 | F10: Till | G10: 19299.85 | I10: samirgasoil | L10: 80
B11: Billetsde10 | C11: 1460 | D11: alishanrest | E11: 571.51 | F11: sancont | I11: ahmedgasoil | L11: 80
B12: Billetsde5 | C12: 185 | I12: ahmedpeage | L12: 3.8
B13: Monnaie | I13: houcineacompte | L13: 140
B14: Total | C14: =SUM(C9:C13) -> 6415 | I14: acompteyahya | L14: 345
B15: Fonddecaisse | C15: 374 | D15: Total | E15: =SUM(E10:E14) -> 1392.81 | F15: Total | G15: =SUM(G10:G14) -> 19299.85 | I15: DifférenceFondCaisse | L15: =C15-'11'!C15 -> -38
K16: Total | L16: =(SUM(L10:L15))*-1 -> -610.8
A18: LIVRAISONS
A19: CODECLIENT | B19: PaiementsChèques | E19: Montant | F19: Banque | G19: Numero | H19: Remarques | L19: SAP
A20: c6940 | B20: mcvlavillette | E20: 327.78 | F20: sg | G20: 75 | L20: ok
A21: c6881 | B21: lapyramide | E21: 498.04 | F21: lcl | G21: 2232938 | L21: ok
A22: c1640 | B22: ancreperie | E22: 259.85 | F22: bnp | G22: 6704518 | H22: ancienpaiement | L22: ok
A23: c6431 | B23: pandaexpress | E23: 307.81 | F23: cic | G23: 3944333 | L23: ok
A24: c4168 | B24: kchimaek | E24: 282.6 | F24: bnp | G24: 9427107 | L24: ok
A25: c4494 | B25: mcvdaumesnil | E25: 270.89 | F25: bred | G25: 8622365 | L25: ok
A26: c4492 | B26: masmaris | E26: 322.62 | F26: cic | G26: 3895400 | L26: ok
A27: c1465 | B27: delicedebeyrouth | E27: 681.13 | F27: sg | G27: 3000484 | L27: ok
A28: c3476 | B28: victoria168 | E28: 573.41 | F28: sg | G28: 300 | L28: ok
A29: c6470 | B29: rannouch | E29: 304.68 | F29: bnp | G29: 1681133 | L29: ok
A30: c4548 | B30: cotepigalle | E30: 225.73 | F30: bpop | G30: 494 | L30: ok
A38: CODECLIENT | B38: PaiementsEspèces | E38: Montant | F38: Remarques | L38: SAP
A39: c3469 | B39: boulangeriemehdaoui | E39: 692.85 | L39: ok
A40: c6330 | B40: adnan | E40: 120.5 | L40: ok
A41: c4031 | B41: lewarner | E41: 304.44 | L41: ok
B42: extran-c-f | E42: 616.43 | L42: ok
A48: CODECLIENT | B48: PaiementsCBSite | E48: Montant | F48: Remarques | L48: SAP
A53: CODECLIENT | B53: PaiementsCBTéléphone | E53: Montant | F53: Remarques | L53: SAP
C54: 802.36 | D54: cari versailles
C55: 675.28 | D55: cqfd
C56: 689.72 | D56: cqfd
C57: 340.26 | D57: new
A58: CODECLIENT | B58: Virements | E58: Montant | F58: Remarques | L58: SAP
B59: FIZAN | E59: 578.85 | L59: ok
B60: KDGDISTRIBUTION | E60: 8815.92 | L60: ok
B61: S,A,S,HASSANIGROSSISTE | E61: 4231.4 | L61: ok
B62: S,A,R,L,SMASHSMASH78 | E62: 305.84 | L62: ok
B63: KANDALALKHALFIABDELADIM | E63: 2986.94 | L63: ok
B64: SUSHI+SNACKFOOD | E64: 3960.09 | L64: ok
B65: S,A,S,CHEZNINOUFASTFOOD | E65: 467.57 | L65: ok
B66: CHULAVISTA | E66: 302.6 | L66: ok
B67: BIBO | E67: 420 | L67: ok
B68: FUTURSOLEIL | E68: 413.07 | L68: ok
B69: CHICKENASIA | E69: 142.11 | L69: ok
B70: VIVAUNGUTORIENTALE | E70: 436.88 | L70: ok
... B209: MOUSTACHEETF | E209: 695.98 | L209: ok
A210: CODECLIENT | B210: Livraisonsnonpayées | E210: Montant | F210: Remarques | L210: SAP
A211: c4800 | B211: shameem | E211: 830.41 | L211: ok
A212: c6288 | B212: sushikekkoo | E212: 386.12 | L212: ok
A213: c1640 | B213: ancreperie | E213: 167.17 | L213: ok
A214: c7763 | B214: luks | E214: 322.77 | L214: ok
A215: c5550 | B215: yohan | E215: 458.13 | L215: ok
A216: c7336 | B216: scone | E216: 781.97 | L216: ok
A217: c5970 | B217: djerba | E217: 696.75 | L217: ok
A218: c2445 | B218: sushi&snack | E218: 342.24 | L218: ok
A219: c2820 | B219: sarlenes | E219: 540.81 | L219: ok
A220: c4357 | B220: burgeriste | E220: 414.54 | L220: ok
A221: c6075 | B221: bsypt | E221: 401.62 | L221: ok
A222: c7634 | B222: wokfactory | E222: 1081.52 | L222: ok
... A230: c63801 | B230: lassaad | E230: 582.77 | L230: ok
B233: TOTALESPECES | E233: =SUM(E39:E47) -> 1734.22
B234: TOTALCHEQUES | E234: =SUM(E20:E37) -> 4054.54
B235: TOTALCBInternet&Phone | E235: =SUM(E49:E57) -> 0

Sheet 14
G1: no002797962000 | I1: DATE | J1: 46126
G2: no002797762190
E3: RemiseBancaire(SAP) | G3: no002797614200 | I3: EXCEL
E4: Espèces | F4: 10170 | G4: no002797811780 | I4: ESPECES | K4: =E198+C17 -> 10174.53
E5: Chèques | F5: 2324.01 | G5: no32324,01 | I5: CHEQUES | K5: =E18+E199 -> 2324.01
E6: Monnaienondéposée | F6: 4.53 | I6: CARTECREDIT | K6: =G18+E200 -> 18118.33
I7: VIREMENT | K7: =SUM(E62:E174) -> 244293.16
B8: CaisseEspèces | D8: Caissechèques | F8: CaisseCB
B9: Billetsde50 | C9: 1700 | D9: Client | E9: Montant | F9: Client | G9: Montant | I9: Dépenses:Essence,Divers | L9: Montant
B10: Billetsde20 | C10: 2220 | D10: alishanrest | E10: 275.87 | F10: Till | G10: 18118.33 | I10: HOCINEGASOIL | L10: 80
B11: Billetsde10 | C11: 5970 | F11: sancont | I11: SKANDERGASOIL | L11: 80
I12: ZOUHIRACOMPTE | L12: 170
I13: YAHYARENDUARGENT | L13: 141
I14: SONIAACOMPTE | L14: 720
B15: Billetsde5 | C15: 190 | I15: SAMIRGASOIL | L15: 200
B16: Monnaie | I16: ABUBAKARGASOIL | L16: 80
B17: Total | C17: =SUM(C9:C16) -> 10080 | I17: AHMEDACOMPTE | L17: 390
B18: Fonddecaisse | C18: 317 | D18: Total | E18: =SUM(E10:E17) -> 275.87 | F18: Total | G18: =SUM(G10:G17) -> 18118.33 | I18: DifférenceFondCaisse | L18: =C18-'13'!C15 -> -57
K19: Total | L19: =(SUM(L10:L18))*-1 -> -1804
A21: LIVRAISONS
A22: CODECLIENT | B22: PaiementsChèques | E22: Montant | F22: Banque | G22: Numero | H22: Remarques | L22: SAP
A23: C6940 | B23: MCVLAVILLETTE | E23: 322.51 | F23: SG | G23: 76 | L23: OK
A24: C3186 | B24: VIFZAEKA | E24: 1725.63 | F24: CIC | G24: 3044072 | L24: OK
A41: CODECLIENT | B41: PaiementsEspèces | E41: Montant | F41: Remarques | L41: SAP
A42: C6159 | B42: ROSMINS | E42: 94.53 | F42: ANCIENPAIEMENT | L42: OK
A51: CODECLIENT | B51: PaiementsCBSite | E51: Montant | F51: Remarques | L51: SAP
A56: CODECLIENT | B56: PaiementsCBTéléphone | E56: Montant | F56: Remarques | L56: SAP
C57: 802.36 | D57: cari versailles
C58: 675.28 | D58: cqfd
C59: 689.72 | D59: cqfd
C60: 340.26 | D60: new
A61: CODECLIENT | B61: Virements | E61: Montant | F61: Remarques | L61: SAP
B62: S,A,S,HETNMARKET | E62: 284.5 | L62: ok
B63: CHICKENASIA | E63: 125.96 | L63: ok
B64: CHICKENSPOT | E64: 232.63 | L64: ok
B65: SUSHIBOX | E65: 315.68 | L65: ok
B66: SARLBKK1 | E66: 316.87 | L66: ok
B67: LEFKA | E67: 737.29 | L67: ok
B68: SASTENDERSBROTHERS | E68: 1047.27 | L68: ok
B69: S,A,R,L,LAFRITEDUNORD | E69: 438.66 | L69: ok
B70: ELMAHIRESTAURANT | E70: 1513.48 | L70: ok
B71: DELICESDEBEYROUTH | E71: 1166.97 | L71: ok
B72: TORINO | E72: 338.9 | L72: ok
B73: BURGERISTE | E73: 414.54 | L73: ok
... B174: FUTURSOLEIL | E174: 317.13 | L174: ok
A175: CODECLIENT | B175: Livraisonsnonpayées | E175: Montant | F175: Remarques | L175: SAP
A176: C7100 | B176: LEKINKS | E176: 1941.75 | F176: PAYECBLIEN | L176: OK
A177: C2592 | B177: VILLEJUIFSPOT | E177: 1700 | L177: OK
A178: C7084 | B178: DIEUNE | E178: 430.53 | L178: OK
A179: C7675 | B179: TOKYORAMA | E179: 184.45 | L179: OK
A180: C4308 | B180: THAIMING | E180: 443.72 | L180: OK
A181: C2886 | B181: NEHAAUBERVILLIERS | E181: 764.24 | L181: OK
A182: C1259 | B182: SRS | E182: 960.49 | L182: OK
A183: C3127 | B183: MOUSTACHE | E183: 352.03 | L183: OK
A184: C7164 | B184: KRUNCHY | E184: 393.67 | L184: OK
A185: C7774 | B185: WABA | E185: 349.47 | L185: OK
A186: C7143 | B186: ABRAJ | E186: 1799.38 | L186: OK
A187: C4368 | B187: VANAPRIL | E187: 445.56 | L187: OK
A188: C7604 | B188: MAXIME | E188: 624.68 | L188: OK
... A196: C5431 | B196: DREAMFACTORY | E196: 3430.17 | L196: OK
B198: TOTALESPECES | E198: =SUM(E42:E50) -> 94.53
B199: TOTALCHEQUES | E199: =SUM(E23:E40) -> 2048.14
B200: TOTALCBInternet&Phone | E200: =SUM(E52:E60) -> 0

Sheet 15
I1: DATE | J1: 46127
E3: RemiseBancaire(SAP) | G3: no002798132130 | I3: EXCEL
E4: Espèces | F4: 6900 | G4: no002798084770 | I4: ESPECES | K4: =E287+C14 -> 6905.92
E5: Chèques | F5: 4466.21 | G5: no104466,21 | I5: CHEQUES | K5: =E15+E288 -> 4466.21
E6: Monnaienondéposée | F6: 6 | I6: CARTECREDIT | K6: =G15+E289 -> 64535.96
I7: VIREMENT | K7: =SUM(E115:E256) -> 354933.52
B8: CaisseEspèces | D8: Caissechèques | F8: CaisseCB
B9: Billetsde50 | C9: 1550 | D9: Client | E9: Montant | F9: Client | G9: Montant | I9: Dépenses:Essence,Divers | L9: Montant
B10: Billetsde20 | C10: 1780 | D10: alishanrest | E10: 498.3 | F10: Till | G10: 19899.16 | I10: ahmedpeage | L10: 3.8
B11: Billetsde10 | C11: 2130 | D11: lemeraude | E11: 596.18 | F11: sancont
B12: Billetsde5 | C12: 60
B13: Monnaie
B14: Total | C14: =SUM(C9:C13) -> 5520
B15: Fonddecaisse | C15: 276 | D15: Total | E15: =SUM(E10:E14) -> 1094.48 | F15: Total | G15: =SUM(G10:G14) -> 19899.16 | I15: DifférenceFondCaisse | L15: =C15-'14'!C18 -> -41
K16: Total | L16: =(SUM(L10:L15))*-1 -> 37.2
A18: LIVRAISONS
A19: CODECLIENT | B19: PaiementsChèques | E19: Montant | F19: Banque | G19: Numero | H19: Remarques | L19: SAP
A20: C4647 | B20: TAMKINE | E20: 234.51 | F20: CM | G20: 6375623 | L20: OK
A21: C7212 | B21: HUGOGAO | E21: 448.11 | F21: CE | G21: 473 | L21: OK
A22: C3476 | B22: VICTORIA168 | E22: 360.69 | F22: SG | G22: 301 | L22: OK
A23: C5144 | B23: MCVFAIDHERBE | E23: 341.5 | F23: BRED | G23: 7051123 | L23: OK
A24: C4168 | B24: KCHIMAEK | E24: 272.06 | F24: BNP | G24: 9427108 | L24: OK
A25: C1376 | B25: DELICEHOUSE | E25: 392.07 | F25: CE | G25: 9978480 | L25: OK
A26: C6676 | B26: HUGOGAO | E26: 293.06 | F26: BNP | G26: 2640913 | L26: OK
A27: C3942 | B27: SASLATIF | E27: 1029.73 | F27: BPOP | G27: 104 | L27: OK
A38: CODECLIENT | B38: PaiementsEspèces | E38: Montant | F38: Remarques | L38: SAP
A39: C9999 | B39: VCCROUSTYFAMILY | E39: 959.69 | L39: OK
A40: C3017 | B40: PFBABYLONE | E40: 426.23 | L40: OK
A48: CODECLIENT | B48: PaiementsCBSite | E48: Montant | F48: Remarques | L48: SAP
B49: 12/03/2026PaiementDCC:SodaryKHAMPRASEUTHTerminé | E49: 357.6 | F49: 2.25 | G49: 355.35 | H49: paypal+cash | L49: ok
B50: 12/03/2026PaiementExpressCheckout:faridboudiharTerminé | E50: 1992.57 | F50: 40.1 | G50: 1952.47 | H50: paypal+cash | L50: ok
B51: 12/03/2026PaiementDCC:ThiNhatHaNGUYENTerminé | E51: 331.15 | F51: 2.09 | G51: 329.06 | H51: paypal+cash | L51: ok
B52: 14/03/2026PaiementExpressCheckout:NinaMetoudiTerminé | E52: 377.3 | F52: 7.8 | G52: 369.5 | H52: paypal+cash | L52: ok
B53: 15/03/2026PaiementDCC:PascalPapillonTerminé | E53: 335.61 | F53: 2.11 | G53: 333.5 | H53: paypal+cash | L53: ok
B54: 15/03/2026PaiementDCC:SASToliaTerminé | E54: 333.91 | F54: 2.1 | G54: 331.81 | H54: paypal+cash | L54: ok
B55: PaiementDCC:LESMARMITESDECATHY 16/03/2026PEROZZIELLOAlexandreTerminé | E55: 847.72 | F55: 5.19 | G55: 842.53 | H55: paypal+cash | L55: ok
B56: 16/03/2026PaiementDCC:VaughnJanesTerminé | E56: 354.93 | F56: 2.23 | G56: 352.7 | H56: paypal+cash | L56: ok
B57: 16/03/2026PaiementExpressCheckout:akramchammamTerminé | E57: 590.42 | F57: 12.06 | G57: 578.36 | H57: paypal+cash | L57: ok
B58: 17/03/2026PaiementDCC:GolamAzamTerminé | E58: 337.51 | F58: 2.13 | G58: 335.38 | H58: paypal+cash | L58: ok
B59: 17/03/2026PaiementExpressCheckout:AnélineCayezTerminé | E59: 995.04 | F59: 20.15 | G59: 974.89 | H59: paypal+cash | L59: ok
B60: 18/03/2026PaiementDCC:AkbarKhanTerminé | E60: 467.24 | F60: 2.9 | G60: 464.34 | H60: paypal+cash | L60: ok
... B108: 11/04/2026PaiementDCC:MaximeRivatTerminé | E108: 2081.98 | F108: 12.59 | G108: 2069.39 | H108: paypal+cash | L108: ok
A109: CODECLIENT | B109: PaiementsCBTéléphone | E109: Montant | F109: Remarques | L109: SAP
C110: 802.36 | D110: cari versailles
C111: 675.28 | D111: cqfd
C112: 689.72 | D112: cqfd
C113: 340.26 | D113: new
A114: CODECLIENT | B114: Virements | E114: Montant | F114: Remarques | L114: SAP
B115: LEBONMANGEUR | E115: 905.12 | L115: ok
B116: S,A,S,CHEZNINOUFASTFOOD | E116: 532 | L116: ok
B117: LAROSEDEBERGERAC | E117: 551.89 | L117: ok
B118: LAROSEDEBERGERAC | E118: 530.88 | L118: ok
B119: S,A,S,CHEZNINOUFASTFOOD | E119: 75.76 | L119: ok
B120: S,A,S,DISTRIDRINKS | E120: 14301.29 | L120: ok
B121: SORAYATARFAIAEI | E121: 4825.3 | L121: ok
B122: DREAMFACTORY | E122: 863.78 | L122: ok
B123: DIPSAMATIC | E123: 11309.74 | L123: ok
B124: SASLPC | E124: 650.31 | L124: ok
B125: SASTENDERSBROTHERS | E125: 283.51 | L125: ok
B126: DREAMFACTORY | E126: 2819.66 | L126: ok
... B256: FRITESDOREES29244,6011/03 | E256: 29244.6 | L256: ok
A257: CODECLIENT | B257: Livraisonsnonpayées | E257: Montant | F257: Remarques | L257: SAP
A258: C5550 | B258: YOHAN | E258: 458.13 | L258: OK
A259: C7478 | B259: KFE | E259: 1651.04 | L259: OK
A260: C1727 | B260: VIVAUNGUT | E260: 338.88 | L260: OK
A261: C6367 | B261: CREPESURMESURE | E261: 892.14 | L261: OK
A262: C7720 | B262: BRUT | E262: 293.5 | L262: OK
A263: C4523 | B263: NEHASTDENIS | E263: 1084.64 | L263: OK
A264: C5842 | B264: GARBA | E264: 521.15 | L264: OK
A265: C7741 | B265: O'GARDEN | E265: 423.45 | L265: OK
A266: C3287 | B266: BUDDIES | E266: 413.54 | L266: OK
A267: C6018 | B267: MAMIFOOD | E267: 1499.43 | L267: OK
A268: C7621 | B268: COVA | E268: 339.22 | L268: OK
A269: C6294 | B269: CROUSTYFAMILY | E269: 1511.68 | L269: OK
... A285: C5714 | B285: OUNISSA | E285: 360.35 | L285: OK
B287: TOTALESPECES | E287: =SUM(E39:E47) -> 1385.92
B288: TOTALCHEQUES | E288: =SUM(E20:E37) -> 3371.73
B289: TOTALCBInternet&Phone | E289: =SUM(E49:E113) -> 44636.8

Sheet 16
I1: DATE | J1: 46129
E3: RemiseBancaire(SAP) | G3: no002798335295 | I3: EXCEL
E4: Espèces | F4: 7485 | G4: no002798282190 | I4: ESPECES | K4: =E154+C14 -> 7489.95
E5: Chèques | F5: 5871.81 | G5: no75871,81 | I5: CHEQUES | K5: =E15+E155 -> 5871.81
E6: Monnaienondéposée | F6: 4.95 | I6: CARTECREDIT | K6: =G15+E156 -> 95422.85
I7: VIREMENT | K7: =SUM(E129:E138) -> 0
B8: CaisseEspèces | D8: Caissechèques | F8: CaisseCB
B9: Billetsde50 | C9: 2950 | D9: Client | E9: Montant | F9: Client | G9: Montant | I9: Dépenses:Essence,Divers | L9: Montant
B10: Billetsde20 | C10: 2280 | D10: maxchicken | E10: 584.86 | F10: Till | G10: 23215.07 | I10: SAMIR | L10: 80
B11: Billetsde10 | C11: 1560 | D11: ausundine | E11: 296.21 | F11: sancont | I11: skandargasoil | L11: 70
B12: Billetsde5 | C12: 65 | I12: ahmedgasoil | L12: 40
B13: Monnaie | I13: abubakarrestsalarymars2026 | L13: 100
B14: Total | C14: =SUM(C9:C13) -> 6855 | I14: ahmed | L14: 20
B15: Fonddecaisse | C15: 250 | D15: Total | E15: =SUM(E10:E14) -> 881.07 | F15: Total | G15: =SUM(G10:G14) -> 23215.07 | I15: DifférenceFondCaisse | L15: =C15-'15'!C15 -> -26
K16: Total | L16: =(SUM(L10:L15))*-1 -> -284
A18: LIVRAISONS
A19: CODECLIENT | B19: PaiementsChèques | E19: Montant | F19: Banque | G19: Numero | H19: Remarques | L19: SAP
A20: C7452 | B20: MARKETDEPOTPSB | E20: 2792.16 | F20: CAIXAGERAL | G20: 5761216 | H20: EXTRASURPLACE | L20: OK
A21: C1541 | B21: SarlCdr | E21: 270.83 | F21: BP | G21: 6383 | L21: OK
A22: c3063 | B22: SASUZOYA | E22: 174.5 | F22: bp | G22: 660 | L22: ok
A23: c3757 | B23: SASTHON | E23: 1411.27 | F23: lcl | G23: 933427 | L23: ok
A24: c6508 | B24: RannouchExpress | E24: 341.98 | F24: bnp | G24: 1681100 | L24: ok
A38: CODECLIENT | B38: PaiementsEspèces | E38: Montant | F38: Remarques | L38: SAP
A39: c5527 | B39: SNCTABACDUTROCADERO | E39: 332.63 | L39: ok
A40: c7735 | B40: RAPIDEFOOD | E40: 260 | L40: ok
A41: c0993 | B41: CAPPADOCE | E41: 42.32 | F41: EXTRA | L41: ok
A48: CODECLIENT | B48: PaiementsCBSite | E48: Montant | F48: Remarques | L48: SAP
B49: 12/03/2026 Paiement DCC: Sodary KHAMPRASEUTH Terminé | E49: 357.6 | F49: 2.25 | G49: 355.35 | H49: paypal + cash
B50: 12/03/2026 Paiement Express Checkout: farid boudihar Terminé | E50: 1992.57 | F50: 40.1 | G50: 1952.47 | H50: paypal + cash
B51: 12/03/2026 Paiement DCC: Thi Nhat Ha NGUYEN Terminé | E51: 331.15 | F51: 2.09 | G51: 329.06 | H51: paypal + cash
B52: 14/03/2026 Paiement Express Checkout: Nina Metoudi Terminé | E52: 377.3 | F52: 7.8 | G52: 369.5 | H52: paypal + cash
B53: 15/03/2026 Paiement DCC: Pascal Papillon Terminé | E53: 335.61 | F53: 2.11 | G53: 333.5 | H53: paypal + cash
B54: 15/03/2026 Paiement DCC: SAS Tolia Terminé | E54: 333.91 | F54: 2.1 | G54: 331.81 | H54: paypal + cash
B55: Paiement DCC: LES MARMITES DE CATHY 16/03/2026 PEROZZIELLO Alexandre Terminé | E55: 847.72 | F55: 5.19 | G55: 842.53 | H55: paypal + cash
B56: 16/03/2026 Paiement DCC: Vaughn Janes Terminé | E56: 354.93 | F56: 2.23 | G56: 352.7 | H56: paypal + cash
B57: 16/03/2026 Paiement Express Checkout: akram chammam Terminé | E57: 590.42 | F57: 12.06 | G57: 578.36 | H57: paypal + cash
B58: 17/03/2026 Paiement DCC: Golam Azam Terminé | E58: 337.51 | F58: 2.13 | G58: 335.38 | H58: paypal + cash
B59: 17/03/2026 Paiement Express Checkout: Anéline Cayez Terminé | E59: 995.04 | F59: 20.15 | G59: 974.89 | H59: paypal + cash
B60: 18/03/2026 Paiement DCC: Akbar Khan Terminé | E60: 467.24 | F60: 2.9 | G60: 464.34 | H60: paypal + cash
... B105: 11/04/2026 Paiement DCC: Maxime Rivat Terminé | E105: 2081.98 | F105: 12.59 | G105: 2069.39 | H105: paypal + cash
A106: CODECLIENT | B106: PaiementsCBTéléphone | E106: Montant | F106: Remarques | L106: SAP
A107: c5977 | B107: brandecision | C107: 802.36 | D107: cari versailles | E107: 5051.34 | L107: OK
A108: C7133 | C108: SUSHIHANDGROUP | E108: 2584.43 | L108: OK
A109: C6004 | C109: NEWSOULFOOD | E109: 443.1 | L109: OK
A110: C6641 | C110: leblouge | E110: 1262.31 | L110: ok
A111: C6337 | C111: DYNASHOP | E111: 3222.61 | L111: OK
A112: c5872 | C112: FrédéricJamoteau | E112: 1688.76 | L112: OK
A113: C7604 | C113: maximestefanos | E113: 210.47 | L113: OK
A114: C2718 | C114: LILIANE&ILIANE | E114: 380.15 | L114: OK
A115: C7352 | C115: SMASHHIT | E115: 3175.61 | L115: OK
A116: C7191 | C116: O'Tacos-MCLDISTRIBUTIONLAUDIERCharles | E116: 763.89 | L116: OK
A117: C7763 | C117: LUKSPARIS8 | E117: 322.77 | L117: OK
A118: C7100 | C118: LEKINKS | E118: 2404.95 | L118: OK
A119: C7550 | C119: AQUAGO | E119: 2980.26 | L119: OK
... A124: C7432 | C124: LeMomentDePartage | E124: 689.49 | L124: OK
C125: 675.28 | D125: cqfd
C126: 689.72 | D126: cqfd
C127: 340.26 | D127: new
A128: CODECLIENT | B128: Virements | E128: Montant | F128: Remarques | L128: SAP
A139: CODECLIENT | B139: Livraisonsnonpayées | E139: Montant | F139: Remarques | L139: SAP
A140: c7634 | B140: WokFactory | E140: 814.15 | L140: ok
A141: c6683 | B141: Chickenstate | E141: 1767.85 | L141: ok
A142: c4517 | B142: etoile(18eme) | E142: 1783.53 | L142: ok
A143: c6471 | B143: MozzafiatoParis | E143: 288.8 | L143: ok
A144: c3318 | B144: bombay | E144: 304.18 | F144: livraisondu10/04 | L144: OK
A145: C9997 | B145: VC | E145: 1201.33 | F145: Mosquéé18/02 | L145: OK
A146: C7743 | B146: UNIVERSAL | E146: 6267.21 | L146: OK
B154: TOTALESPECES | E154: =SUM(E39:E47) -> 634.95
B155: TOTALCHEQUES | E155: =SUM(E20:E37) -> 4990.74
B156: TOTALCBInternet&Phone | E156: =SUM(E49:E127) -> 72207.78

Sheet 17
I1: DATE | J1: 46129
E3: RemiseBancaire(SAP) | I3: EXCEL
E4: Espèces | F4: 3735 | G4: no002798533735 | I4: ESPECES | K4: =E89+C14 -> 3734.24
E5: Chèques | F5: 14073.27 | G5: no1514073,27 | I5: CHEQUES | K5: =E15+E90 -> 14073.27
E6: Monnaienondéposée | F6: 9.24 | I6: CARTECREDIT | K6: =G15+E91 -> 16803.8
I7: VIREMENT | K7: =SUM(E59:E64) -> 0
B8: CaisseEspèces | D8: Caissechèques | F8: CaisseCB
B9: Billetsde50 | C9: 800 | D9: Client | E9: Montant | F9: Client | G9: Montant | I9: Dépenses:Essence,Divers | L9: Montant
B10: Billetsde20 | C10: 1520 | D10: alishanrest | E10: 559.87 | F10: Till | G10: 16803.8 | I10: abubakargasoil351camionlivraisin | L10: 80
B11: Billetsde10 | C11: 1190 | F11: sancont | I11: remboursmentgasoilyahya | L11: 70
B12: Billetsde5 | C12: 215 | I12: idreessb | L12: 1000
B13: Monnaie
B14: Total | C14: =SUM(C9:C13) -> 3725
B15: Fonddecaisse | C15: 291 | D15: Total | E15: =SUM(E10:E14) -> 559.87 | F15: Total | G15: =SUM(G10:G14) -> 16803.8 | I15: DifférenceFondCaisse | L15: =C15-'16'!C15 -> 41
K16: Total | L16: =(SUM(L10:L15))*-1 -> -1191
A18: LIVRAISONS
A19: CODECLIENT | B19: PaiementsChèques | E19: Montant | F19: Banque | G19: Numero | H19: Remarques | L19: SAP
A20: c4517 | B20: etoile(18eme) | E20: 1783.53 | F20: lcl | G20: 7340557 | L20: ok
A21: c6171 | B21: SarlTAMASINI | E21: 706.43 | F21: bnp | G21: 8903628 | L21: ok
A22: c7664 | B22: RestaurantCheezy | E22: 558.09 | F22: bnp | G22: 2693024 | L22: ok
A23: c6482 | B23: RannouchCity | E23: 552.23 | F23: bnp | G23: 1681014 | L23: ok
A24: c4215 | B24: BOULANGERIECAJAN | E24: 450.39 | F24: bp | G24: 114 | L24: ok
A25: c3476 | B25: VICTORIA168 | E25: 329.39 | F25: sg | G25: 302 | L25: ok
A26: c1971 | B26: ESCOMPANY | E26: 466.74 | F26: bp | G26: 4486 | L26: ok
A27: c1971 | B27: ESCOMPANY | E27: 520.62 | F27: bp | G27: 4485 | L27: ok
A28: c6940 | B28: MCVLAVILLETTE | E28: 416.84 | F28: sg | G28: 77 | L28: ok
A29: c1513 | B29: EDENDI | E29: 4549.22 | F29: sg | G29: 475 | L29: ok
A30: c4602 | B30: chamastacosguerrida | E30: 992.66 | F30: cic | G30: 3885377 | L30: ok
A31: c4650 | B31: BREADSHOP | E31: 746.85 | F31: bp | G31: 2371 | L31: ok
... A33: c1547 | B33: ANATOLIEN | E33: 873.96 | F33: bp | G33: 9788455 | L33: ok
A38: CODECLIENT | B38: PaiementsEspèces | E38: Montant | F38: Remarques | L38: SAP
E39: 9.24 | F39: retourgasoilaboubaker
A48: CODECLIENT | B48: PaiementsCBSite | E48: Montant | F48: Remarques | L48: SAP
A49: C7161 | B49: SOIXANTE ET ONZE | F49: extra2044,54 | L49: OK
A53: CODECLIENT | B53: PaiementsCBTéléphone | E53: Montant | F53: Remarques | L53: SAP
C54: 802.36 | D54: cari versailles
C55: 675.28 | D55: cqfd
C56: 689.72 | D56: cqfd
C57: 340.26 | D57: new
A58: CODECLIENT | B58: Virements | E58: Montant | F58: Remarques | L58: SAP
A65: CODECLIENT | B65: Livraisonsnonpayées | E65: Montant | F65: Remarques | L65: SAP
A66: c6534 | B66: DEDAMASABEYROUTH | E66: 313.76 | L66: ok
A67: c6108 | B67: LEROCHER | E67: 356.95 | L67: ok
A68: c5550 | B68: YohanSULTAN | E68: 384.94 | L68: ok
A69: c7027 | B69: SUSHIGALEN | E69: 262.27 | L69: ok
A70: c3938 | B70: SPICE'N'GRILL | E70: 713.76 | L70: ok
A71: c6364 | B71: SARLLACREPESURMESURE | E71: 559.55 | L71: ok
A72: c1403 | C72: SARLGOKAL | E72: 530.5 | L72: ok
A73: c5510 | C73: VK | E73: 333.47 | L73: ok
A74: c2789 | C74: SASUBERTHE | E74: 581.45 | L74: ok
A75: c5877 | C75: ANOUARMATOUSSI | E75: 1005.44 | L75: ok
A76: c1409 | C76: FRITESDOREES | E76: 29244.6 | L76: ok
A77: c9999 | C77: ventecomptoirsurplace | E77: 2194.4 | L77: ok
A78: c5083 | B78: Chulavista | E78: 301.31 | L78: ok
A79: c3127 | B79: moustacheetfils | E79: 1975.85 | L79: ok
A80: c7741 | C80: O'GARDEN | E80: 644.7 | L80: ok
A81: c6018 | C81: MamiFood | E81: 2427.43 | L81: ok
A82: c7801 | C82: MARACUJAFOOD&DRINKS | E82: 341.42 | L82: ok
B89: TOTALESPECES | E89: =SUM(E39:E47) -> 9.24
B90: TOTALCHEQUES | E90: =SUM(E20:E37) -> 13513.4
B91: TOTALCBInternet&Phone | E91: =SUM(E49:E57) -> 0

Sheet 18
I1: DATE | J1: 46130
G2: no002798881880
E3: RemiseBancaire(SAP) | G3: no002798686420 | I3: EXCEL
E4: Espèces | F4: 10145 | G4: no002798731845 | I4: ESPECES | K4: =E80+C14 -> 10145
E5: Chèques | F5: 2597.37 | G5: no42597,37 | I5: CHEQUES | K5: =E15+E81 -> 2597.37
E6: Monnaienondéposée | I6: CARTECREDIT | K6: =G15+E82 -> 29315.67
I7: VIREMENT | K7: =SUM(E59:E64) -> 0
B8: CaisseEspèces | D8: Caissechèques | F8: CaisseCB
B9: Billetsde50 | C9: 3200 | D9: Client | E9: Montant | F9: Client | G9: Montant | I9: Dépenses:Essence,Divers | L9: Montant
B10: Billetsde20 | C10: 3220 | D10: 3afoods | E10: 423.6 | F10: Till | G10: 29315.67 | I10: hocinegasoil | L10: 80
B11: Billetsde10 | C11: 3580 | D11: buffetgare | E11: 805.26 | F11: sancont | I11: samirgasoiladblu | L11: 232
B12: Billetsde5 | C12: 145 | D12: leforentin | E12: 802.43
B13: Monnaie | D13: alishanrest | E13: 566.08
B14: Total | C14: =SUM(C9:C13) -> 10145
B15: Fonddecaisse | C15: 253 | D15: Total | E15: =SUM(E10:E14) -> 2597.37 | F15: Total | G15: =SUM(G10:G14) -> 29315.67 | I15: DifférenceFondCaisse | L15: =C15-'17'!C15 -> -38
K16: Total | L16: =(SUM(L10:L15))*-1 -> -274
A18: LIVRAISONS
A19: CODECLIENT | B19: PaiementsChèques | E19: Montant | F19: Banque | G19: Numero | H19: Remarques | L19: SAP
A38: CODECLIENT | B38: PaiementsEspèces | E38: Montant | F38: Remarques | L38: SAP
A48: CODECLIENT | B48: PaiementsCBSite | E48: Montant | F48: Remarques | L48: SAP
A53: CODECLIENT | B53: PaiementsCBTéléphone | E53: Montant | F53: Remarques | L53: SAP
C54: 802.36 | D54: cari versailles
C55: 675.28 | D55: cqfd
C56: 689.72 | D56: cqfd
C57: 340.26 | D57: new
A58: CODECLIENT | B58: Virements | E58: Montant | F58: Remarques | L58: SAP
A65: CODECLIENT | B65: Livraisonsnonpayées | E65: Montant | F65: Remarques | L65: SAP
B80: TOTALESPECES | E80: =SUM(E39:E47) -> 0
B81: TOTALCHEQUES | E81: =SUM(E20:E37) -> 0
B82: TOTALCBInternet&Phone | E82: =SUM(E49:E57) -> 0

Sheet 19
I1: DATE | J1: 46131
E3: RemiseBancaire(SAP) | I3: EXCEL
E4: Espèces | I4: ESPECES | K4: =E80+C14 -> 0
E5: Chèques | I5: CHEQUES | K5: =E15+E81 -> 0
E6: Monnaienondéposée | I6: CARTECREDIT | K6: =G15+E82 -> 0
I7: VIREMENT | K7: =SUM(E59:E64) -> 0
B8: CaisseEspèces | D8: Caissechèques | F8: CaisseCB
B9: Billetsde50 | D9: Client | E9: Montant | F9: Client | G9: Montant | I9: Dépenses:Essence,Divers | L9: Montant
B10: Billetsde20 | F10: Till
B11: Billetsde10 | F11: sancont
B12: Billetsde5
B13: Monnaie
B14: Total | C14: =SUM(C9:C13) -> 0
B15: Fonddecaisse | D15: Total | E15: =SUM(E10:E14) -> 0 | F15: Total | G15: =SUM(G10:G14) -> 0 | I15: DifférenceFondCaisse | L15: =C15-'18'!C15 -> -253
K16: Total | L16: =(SUM(L10:L15))*-1 -> 253
A18: LIVRAISONS
A19: CODECLIENT | B19: PaiementsChèques | E19: Montant | F19: Banque | G19: Numero | H19: Remarques | L19: SAP
A38: CODECLIENT | B38: PaiementsEspèces | E38: Montant | F38: Remarques | L38: SAP
A48: CODECLIENT | B48: PaiementsCBSite | E48: Montant | F48: Remarques | L48: SAP
A53: CODECLIENT | B53: PaiementsCBTéléphone | E53: Montant | F53: Remarques | L53: SAP
C54: 802.36 | D54: cari versailles
C55: 675.28 | D55: cqfd
C56: 689.72 | D56: cqfd
C57: 340.26 | D57: new
A58: CODECLIENT | B58: Virements | E58: Montant | F58: Remarques | L58: SAP
A65: CODECLIENT | B65: Livraisonsnonpayées | E65: Montant | F65: Remarques | L65: SAP
B80: TOTALESPECES | E80: =SUM(E39:E47) -> 0
B81: TOTALCHEQUES | E81: =SUM(E20:E37) -> 0
B82: TOTALCBInternet&Phone | E82: =SUM(E49:E57) -> 0

Sheet 20
G1: NO 01805004 2975 | I1: DATE | J1: 46132
G2: NO 00279905 4125
E3: RemiseBancaire(SAP) | G3: NO 00279910 1880 | I3: EXCEL
E4: Espèces | F4: 10250 | G4: NO 00279893 1270 | I4: ESPECES | K4: =E207+C15 -> 10255.75
E5: Chèques | F5: 4133.3 | G5: NO 8 4133,30 | I5: CHEQUES | K5: =E16+E208 -> 4133.3
E6: Monnaienondéposée | F6: 5.75 | I6: CARTECREDIT | K6: =G16+E209 -> 26068.2
I7: VIREMENT | K7: =SUM(E62:E164) -> 269425.29
B8: CaisseEspèces | D8: Caissechèques | F8: CaisseCB
B9: Billetsde50 | C9: 1500 | D9: Client | E9: Montant | F9: Client | G9: Montant | I9: Dépenses:Essence,Divers | L9: Montant
B10: Billetsde20 | C10: 2500 | D10: AU SUN DINE | E10: 849.92 | F10: Till | G10: 19916.27 | I10: SKANDER | L10: 65
B11: Billetsde10 | C11: 3150 | D11: ALISHAN REST | E11: 708.16 | F11: sancont | I11: SAMIR GASOIL | L11: 140
I12: HOCINE LAVAGE | L12: 20
B13: Billetsde5 | C13: 125 | I13: AHMED GASOIL | L13: 100
B14: Monnaie | I14: ABU BAKAR GASOIL | L14: 80
B15: Total | C15: =SUM(C9:C14) -> 7275 | I15: YOUSRA SALARY | L15: 850
B16: Fonddecaisse | C16: 291 | D16: Total | E16: =SUM(E10:E15) -> 1558.08 | F16: Total | G16: =SUM(G10:G15) -> 19916.27 | I16: DifférenceFondCaisse | L16: =C16-'19'!C15 -> 291
K17: Total | L17: =(SUM(L10:L16))*-1 -> -1546
A19: LIVRAISONS
A20: CODECLIENT | B20: PaiementsChèques | E20: Montant | F20: Banque | G20: Numero | H20: Remarques | L20: SAP
A21: c1640 | B21: ANCREPERIE | E21: 169.17 | F21: bnp | G21: 6704523 | H21: anciennecommande | L21: ok
A22: C6881 | B22: Lapyramide | E22: 373.43 | F22: lcl | G22: 2232929 | L22: ok
A23: C3476 | B23: VICTORIA 168 | E23: 512.81 | F23: SG | G23: 303 | L23: OK
A24: C4561 | B24: Delice du colisee | E24: 454.75 | F24: SG | G24: 1001959 | L24: OK
A25: C1222 | B25: LE RELAIS D'OR | E25: 548.07 | F25: CIC | G25: 2599553 | L25: OK
A26: C6940 | B26: MCV LA VILLETTE | E26: 516.99 | F26: SG | G26: 78 | L26: OK
A39: CODECLIENT | B39: PaiementsEspèces | E39: Montant | F39: Remarques | L39: SAP
A40: c4474 | B40: CASAPRONTO | E40: 400 | F40: reste264,65apayerparvirement | L40: ok
A41: c3017 | B41: PFCARDINET(MATHIEUBoulangerie) | E41: 399.37 | L41: ok
A42: c3404 | B42: O'CROUSTY | E42: 2181.38 | L42: ok
A48: CODECLIENT | B48: PaiementsCBSite | E48: Montant | F48: Remarques | L48: SAP
A49: C6108 | B49: LEROCHER | E49: 316.89 | L49: OK
A50: C1403 | C50: SARLGOKAL | E50: 530.5 | L50: OK
A51: C7550 | C51: AQUAGO | E51: 1627.28 | L51: OK
A52: C4927 | C52: PizzeriaSarda | E52: 2637.79 | L52: OK
A53: C653 | B53: DEDAMASABEYROUTH | E53: 313.76 | L53: OK
A54: C7396 | B54: LESSAVEURSDEGRETZ | E54: 725.71 | L54: OK
A56: CODECLIENT | B56: PaiementsCBTéléphone | E56: Montant | F56: Remarques | L56: SAP
C57: 802.36 | D57: cari versailles
C58: 675.28 | D58: cqfd
C59: 689.72 | D59: cqfd
C60: 340.26 | D60: new
A61: CODECLIENT | B61: Virements | E61: Montant | F61: Remarques | L61: SAP
B62: RANY | E62: 389.53 | L62: ok
B63: BOULANGERIEDEL | E63: 587 | L63: ok
B64: SCONE | E64: 781.17 | L64: ok
B65: ATS | E65: 407.12 | L65: ok
B66: ATS | E66: 481.14 | L66: ok
B67: SARLV,V | E67: 326.83 | L67: ok
B68: SCONE | E68: 1292.18 | L68: ok
B69: SCONE | E69: 574.29 | L69: ok
B70: SCONE | E70: 958.11 | L70: ok
B71: SASCASAPRONTO | E71: 264.65 | L71: ok
B72: QFDBEAUVAIS | E72: 1223.27 | L72: ok
B73: OGARDEN | E73: 514.97 | L73: ok
... B164: WABAFOOD | E164: 375.83 | L164: ok
A165: CODECLIENT | B165: Livraisonsnonpayées | E165: Montant | F165: Remarques | L165: SAP
A166: c7518 | B166: OSV | E166: 1927.33 | L166: ok
A167: c3617 | B167: mnh | E167: 1421.01 | L167: ok
A168: c7675 | B168: TOKYORAMA(O'9POKE) | E168: 239.77 | L168: ok
A169: c7675 | B169: TOKYORAMA(O'9POKE) | E169: 574.55 | L169: ok
A170: c7671 | B170: mahendranruhunaveni | E170: 381.79 | L170: ok
A171: c6658 | B171: SASBoulangeriemaisondessaveurs | E171: 587 | L171: ok
A172: c6918 | B172: MEOKJA | E172: 268.78 | L172: ok
A173: c5762 | B173: ThinhungNguyen | E173: 321.13 | L173: ok
A174: c1640 | B174: ANCREPERIE | E174: 300.4 | L174: ok
A175: c4368 | C175: RestaurantVanApril | E175: 407.12 | L175: ok
A176: c7336 | C176: SCONE | E176: 1522.11 | L176: ok
A177: c4494 | C177: MCVDaumesnil | E177: 413.73 | L177: ok
A178: c7483 | C178: CENTRALEFOOD | E178: 43031.34 | L178: ok
A179: c3208 | C179: AR-Chickenspot | E179: 893.65 | L179: ok
A180: c7596 | C180: DEEPKITCHEN | E180: 948.74 | L180: ok
A181: c7744 | C181: CroustyTwo | E181: 3030.34 | L181: ok
A182: c3458 | C182: SarlSAMIE(Chickenspot) | E182: 751.67 | L182: ok
A183: c4299 | C183: les5freres | E183: 521.52 | H183: erreur | L183: ok
A184: C5729 | C184: JoeBurger | E184: 346.27 | L184: OK
A185: C5863 | C185: KINGFOOD | E185: 351.56 | L185: OK
A186: C1465 | C186: DELICEDEBEYROUTHIHLIBAN | E186: 697.5 | L186: OK
A187: C4379 | C187: SUKISOBA | E187: 403.16 | L187: ok
A188: c5702 | B188: FahadMuhammad | E188: 326.18 | L188: ok
A189: c1259 | C189: SRS CHICKEN SPOT (trembley) | E189: 557.73 | L189: ok
A190: c4084 | C190: SOGEMAT | E190: 4414.44 | L190: OK
A191: C7164 | C191: Ilyes El Morabit | E191: 355.19 | L191: OK
A192: C2581 | C192: AL IHSAN | E192: 2531.16 | L192: OK
A193: C1732 | C193: sarl fried chicken | E193: 371.45 | L193: OK
A194: C7596 | C194: DEEPKITCHEN | E194: 948.74 | L194: OK
A195: C1213 | C195: AL IHTIMAM BIM S | E195: 948.45 | L195: OK
A196: C6683 | C196: Chicken state | E196: 1726.03 | L196: OK
A197: C2445 | C197: SUSHI & SNACK FOOD | E197: 321.19 | L197: OK
A198: C1222 | C198: LE RELAIS D'OR | E198: 821.94 | L198: OK
B207: TOTALESPECES | E207: =SUM(E40:E47) -> 2980.75
B208: TOTALCHEQUES | E208: =SUM(E21:E38) -> 2575.22
B209: TOTALCBInternet&Phone | E209: =SUM(E49:E60) -> 6151.93

Sheet 21
I1: DATE | J1: 46133
E3: RemiseBancaire(SAP) | G3: NO 01552712 3775 | I3: EXCEL
E4: Espèces | F4: 5855 | G4: NO 01552707 2080 | I4: ESPECES | K4: =E106+C17 -> 5855
E5: Chèques | F5: 5091.62 | G5: NO 8 4699,41 | I5: CHEQUES | K5: =E18+E107 -> 4699.41
E6: Monnaienondéposée | I6: CARTECREDIT | K6: =G18+E108 -> 33181.56
I7: VIREMENT | K7: =SUM(E72:E77) -> 0
B8: CaisseEspèces | D8: Caissechèques | F8: CaisseCB
B9: Billetsde50 | C9: 1200 | D9: Client | E9: Montant | F9: Client | G9: Montant | I9: Dépenses:Essence,Divers | L9: Montant
B10: Billetsde20 | C10: 2300 | D10: ALISHAN REST | E10: 212.89 | F10: Till | G10: 23821.13 | I10: AMOR GASOIL | L10: 150
B11: Billetsde10 | C11: 2030 | D11: MAX CHICKEN | E11: 461.19 | F11: sancont | I11: AMOR SAMDI | L11: 65
I12: HOUCINE GASOIL | L12: 80
I13: SAMIR GASOIL | L13: 250
B14: Billetsde5 | C14: 275 | I14: SAMIR LAVAGE | L14: 50
I15: SKANDAR GASOIL | L15: 85
B16: Monnaie | I16: FIRDAWAS SALARIE | L16: 70
B17: Total | C17: =SUM(C9:C16) -> 5805 | I17: AMOR LAVAGE | L17: 28
B18: Fonddecaisse | C18: 416 | D18: Total | E18: =SUM(E10:E17) -> 674.08 | F18: Total | G18: =SUM(G10:G17) -> 23821.13 | I18: DifférenceFondCaisse | L18: =C18-'20'!C16 -> 125
K19: Total | L19: =(SUM(L10:L18))*-1 -> -903
A21: LIVRAISONS
A22: CODECLIENT | B22: PaiementsChèques | E22: Montant | F22: Banque | G22: Numero | H22: Remarques | L22: SAP
A23: c4204 | B23: Kashmir express | E23: 341.09 | F23: lcl | G23: 2722684 | L23: ok
A24: c6643 | B24: BK FAMILY | E24: 2150.33 | F24: sg | G24: 155 | L24: ok
A25: c5161 | B25: K-CHI | E25: 260.41 | F25: bnp | G25: 9427206 | L25: ok
A26: c4168 | B26: restaurant k- chimaek | E26: 263.57 | F26: bnp | G26: 9427109 | L26: ok
A27: C4647 | B27: TAMKINE 1 | E27: 322.72 | F27: CM | G27: 6375632 | L27: OK
A28: C3237 | B28: LE MAGHREB | E28: 687.21 | F28: LCL | G28: 6786167 | L28: OK
A40: CODECLIENT | B40: PaiementsEspèces | E40: Montant | F40: Remarques | L40: SAP
B41: SAMIR | E41: 50 | F41: RETOUR GASIL
A50: CODECLIENT | B50: PaiementsCBSite | E50: Montant | F50: Remarques | L50: SAP
B51: 12/04/2026 Paiement DCC: Krunchy Sarcelles Terminé | E51: 418.93 | F51: 2.61 | G51: 416.32 | H51: paypal + cash | L51: ok
B52: 13/04/2026 Paiement Express Checkout: SARL EL DORADO Terminé | E52: 1398.24 | F52: 28.21 | G52: 1370.03 | H52: paypal + cash | L52: ok
B53: 13/04/2026 Paiement DCC: Séverine Richard Terminé | E53: 548.2 | F53: 3.39 | G53: 544.81 | H53: paypal + cash | L53: ok
B54: 13/04/2026 Paiement DCC: Sodary KHAMPRASEUTH Terminé | E54: 419.79 | F54: 2.62 | G54: 417.17 | H54: paypal + cash | L54: ok
B55: 13/04/2026 Paiement DCC: Laura Sonzini Terminé | E55: 1911.68 | F55: 11.57 | G55: 1900.11 | H55: paypal + cash | L55: ok
B56: 14/04/2026 Paiement DCC: Pascal Papillon Terminé | E56: 470.59 | F56: 2.92 | G56: 467.67 | H56: paypal + cash | L56: ok
B57: 14/04/2026 Paiement DCC: Golam Azam Terminé | E57: 328.54 | F57: 2.07 | G57: 326.47 | H57: paypal + cash | L57: ok
B58: 14/04/2026 Paiement Express Checkout: OUNISSA YAZID Terminé | E58: 360.35 | F58: 7.46 | G58: 352.89 | H58: paypal + cash | L58: ok
B59: Paiement Express Checkout: SANDRINE 14/04/2026 QUEVILLON Terminé Identifiant: 8HY534866X7790114 | E59: 484.42 | F59: 9.94 | G59: 474.48 | H59: paypal + cash | L59: ok
B60: 17/04/2026 Paiement Express Checkout: thinhung nguyen Terminé | E60: 321.13 | F60: 6.67 | G60: 314.46 | H60: paypal + cash | L60: ok
B61: 17/04/2026 Paiement DCC: mahendran ruhunaveni Terminé | E61: 381.79 | F61: 2.39 | G61: 379.4 | H61: paypal + cash | L61: ok
B62: 18/04/2026 Paiement DCC: Golam Azam Terminé | E62: 326.18 | F62: 2.06 | G62: 324.12 | H62: paypal + cash | L62: ok
... B65: 19/04/2026 Paiement DCC: Krunchy Sarcelles Terminé | E65: 355.19 | F65: 2.23 | G65: 352.96 | H65: paypal + cash | L65: ok
A66: CODECLIENT | B66: PaiementsCBTéléphone | E66: Montant | F66: Remarques | L66: SAP
A67: C6263 | B67: MRS DI NAPOLI | C67: 802.36 | D67: cari versailles | E67: 163.76 | F67: EXTRA | L67: OK
A68: C6263 | B68: MRS DI NAPOLI | C68: 675.28 | D68: cqfd | E68: 52.64 | F68: EXTRA | L68: OK
C69: 689.72 | D69: cqfd
C70: 340.26 | D70: new
A71: CODECLIENT | B71: Virements | E71: Montant | F71: Remarques | L71: SAP
A78: CODECLIENT | B78: Livraisonsnonpayées | E78: Montant | F78: Remarques | L78: SAP
A79: c7191 | B79: O'Tacos-MCL DISTRIBUTION LAUDIER Charles | E79: 538.01 | L79: ok
A80: c3287 | B80: BUDDIE'S | E80: 572.69 | L80: ok
A81: c6254 | B81: DISPRO France | E81: 3164.37 | L81: ok
A82: c7621 | B82: COVA SERVICES | E82: 464.82 | L82: ok
A83: c6018 | B83: Mami Food | E83: 2016 | L83: ok
A84: c3232 | B84: FRUIT LUX | E84: 1092.59 | L84: ok
A85: c7799 | B85: Krunsh | E85: 2684.31 | F85: facture du 16/04 | L85: ok
A86: C1513 | B86: EDENDI | E86: 4456.6 | F86: facture du 16/04 | L86: OK
A87: c4114 | C87: la familia | E87: 256.14 | L87: ok
A88: c7742 | C88: O'GARDEN | E88: 353.9 | L88: ok
A89: c5170 | C89: FARMER PARIS | E89: 2140.21 | L89: ok
A90: c2820 | C90: sarl enes | E90: 599.85 | L90: ok
A91: c6194 | C91: assilak | E91: 1221.35 | L91: ok
A92: c6380 | B92: lassaad ben daali | E92: 553.58 | L92: ok
A93: c4368 | B93: Restaurant Van April | E93: 335.95 | L93: ok
A94: c7336 | C94: SC ONE | E94: 994.33 | L94: ok
A95: C7396 | C95: LES SAVEURS DE GRETZ | E95: 669.22 | L95: OK
A96: C6075 | C96: BSY PT | E96: 392.51 | L96: OK
A97: C7634 | C97: Wok Factory | E97: 1192.39 | L97: OK
A98: C7518 | C98: OSV | E98: 569.49 | L98: OK
A99: C7165 | C99: GENERAL FEED | E99: 2277.96 | L99: OK
A100: C3938 | C100: SPICE'N'GRILL Restaurant Halal Indien Moderne | E100: 761.66 | L100: OK
A101: C7143 | C101: STE ABRAJ | E101: 801.64 | L101: OK
B106: TOTALESPECES | E106: =SUM(E41:E49) -> 50
B107: TOTALCHEQUES | E107: =SUM(E23:E39) -> 4025.33
B108: TOTALCBInternet&Phone | E108: =SUM(E51:E70) -> 9360.43

Sheet 22
G1: no 01552747 1950 | I1: DATE | J1: 46134
G2: no 01552727 4560
E3: RemiseBancaire(SAP) | G3: no 01552732 5955 | I3: EXCEL
E4: Espèces | F4: 14120 | G4: no 01552752 1655 | I4: ESPECES | K4: =E85+C14 -> 14126.11
E5: Chèques | F5: 4049.31 | G5: no 10 4049,31 | I5: CHEQUES | K5: =E15+E86 -> 4049.31
E6: Monnaienondéposée | F6: 6.11 | I6: CARTECREDIT | K6: =G15+E87 -> 12502.12
I7: VIREMENT | K7: =SUM(E59:E64) -> 0
B8: CaisseEspèces | D8: Caissechèques | F8: CaisseCB
B9: Billetsde50 | C9: 2000 | D9: Client | E9: Montant | F9: Client | G9: Montant | I9: Dépenses:Essence,Divers | L9: Montant
B10: Billetsde20 | C10: 2060 | D10: alishan rest | E10: 422.91 | F10: Till | G10: 11887.01 | I10: rendu remboursement jk monnaie | L10: 2.83
B11: Billetsde10 | C11: 3400 | F11: sancont | I11: ahmed gasoil | L11: 80
B12: Billetsde5 | C12: 205 | I12: samir lavage | L12: 50
B13: Monnaie
B14: Total | C14: =SUM(C9:C13) -> 7665
B15: Fonddecaisse | C15: 417 | D15: Total | E15: =SUM(E10:E14) -> 422.91 | F15: Total | G15: =SUM(G10:G14) -> 11887.01 | I15: DifférenceFondCaisse | L15: =C15-'21'!C18 -> 1
K16: Total | L16: =(SUM(L10:L15))*-1 -> -133.83
A18: LIVRAISONS
A19: CODECLIENT | B19: PaiementsChèques | E19: Montant | F19: Banque | G19: Numero | H19: Remarques | L19: SAP
A20: c4548 | B20: COTE PIGALLE | E20: 305.84 | F20: bp | G20: 496 | L20: ok
A21: c1855 | B21: FRANPRIX SAVU | E21: 448.6 | F21: lcl | G21: 4142823 | L21: ok
A22: c5144 | B22: MCV FAIDHERBE | E22: 467.01 | F22: bred | G22: 7051124 | L22: ok
A23: c2938 | B23: MCV Dumas | E23: 353.11 | F23: bred | G23: 8738422 | L23: ok
A24: c3647 | B24: AU LEVAIN | E24: 327.84 | F24: la poste | G24: 5673007 | L24: ok
A25: c2545 | B25: BRN TASTY | E25: 511.95 | F25: bp | G25: 1170 | L25: ok
A26: c1900 | B26: HOT PIZZA 77 | E26: 352.12 | F26: cic | G26: 6361490 | L26: ok
A27: c6758 | B27: selimex | E27: 535.52 | F27: sg | G27: 781 | L27: ok
A28: c6599 | B28: Shuaib cassim | E28: 324.41 | F28: lcl | G28: 324.41 | L28: ok
A38: CODECLIENT | B38: PaiementsEspèces | E38: Montant | F38: Remarques | L38: SAP
A39: c6973 | B39: jk distribution | E39: 4510 | F39: surplace | L39: ok
A40: c2414 | B40: LA ROTISSERIE | E40: 413.8 | L40: ok
A41: c5076 | B41: Burger Dpc | E41: 361.89 | L41: ok
A42: c9999 | B42: vente comptoir sur place | E42: 1125.42 | F42: crousty family | L42: ok
B43: samir retour | E43: 50 | F43: samir retour lavage
A48: CODECLIENT | B48: PaiementsCBSite | E48: Montant | F48: Remarques | L48: SAP
A49: c7396 | B49: LES SAVEURS DE GRETZ | E49: 615.11 | L49: ok
A53: CODECLIENT | B53: PaiementsCBTéléphone | E53: Montant | F53: Remarques | L53: SAP
C54: 802.36 | D54: cari versailles
C55: 675.28 | D55: cqfd
C56: 689.72 | D56: cqfd
C57: 340.26 | D57: new
A58: CODECLIENT | B58: Virements | E58: Montant | F58: Remarques | L58: SAP
A65: CODECLIENT | B65: Livraisonsnonpayées | E65: Montant | F65: Remarques | L65: SAP
A66: c7473 | B66: Jim’s corner | E66: 474.49 | L66: ok
A67: c4800 | B67: SHAMEEM (Chicken spot) | E67: 1158.92 | L67: ok
B68: halal course | E68: 59.9 | F68: halal course 6287
A69: c7604 | B69: maxime stefanos | E69: 713.39 | L69: ok
A70: c4332 | B70: YBB | E70: 394.36 | L70: ok
A71: c7259 | B71: EDEN QASIMI | E71: 713.06 | L71: ok
A72: c7289 | B72: frederic gicquel | E72: 329.58 | L72: ok
A73: c6147 | B73: saint georges France | E73: 501.9 | L73: ok
A74: c7821 | C74: Adbus Shahid Muhammed | E74: 356.3 | L74: ok
A75: c7209 | C75: TENDERS BROTHERS | E75: 512.27 | L75: ok
A76: c7756 | C76: BIDIT RISHEB | E76: 7089.92 | L76: ok
A77: c7692 | C77: SANDRINE QUEVILLON | E77: 490.7 | L77: ok
A78: c4357 | C78: BURGERISTE | E78: 458.85 | L78: ok
A79: c7161 | B79: SOIXANTE ET ONZE | E79: 1759.95 | L79: ok
A80: c2913 | B80: expressomatik | E80: 3661.8 | L80: ok
A81: c6294 | B81: CROUSTY FAMILY | E81: 479.35
B85: TOTALESPECES | E85: =SUM(E39:E47) -> 6461.11
B86: TOTALCHEQUES | E86: =SUM(E20:E37) -> 3626.4
B87: TOTALCBInternet&Phone | E87: =SUM(E49:E57) -> 615.11

Sheet 23
I1: DATE | J1: 46135
E3: RemiseBancaire(SAP) | G3: no 01808819 3920 | I3: EXCEL
E4: Espèces | F4: 7845 | G4: no 01552839 3925 | I4: ESPECES | K4: =E100+C14 -> 7870.34
E5: Chèques | F5: 4274.16 | G5: no 7 4274,16 | I5: CHEQUES | K5: =E15+E101 -> 4274.16
E6: Monnaienondéposée | F6: 25.34 | I6: CARTECREDIT | K6: =G15+E102 -> 37646.45
I7: VIREMENT | K7: =SUM(E70:E75) -> 0
B8: CaisseEspèces | D8: Caissechèques | F8: CaisseCB
B9: Billetsde50 | C9: 2350 | D9: Client | E9: Montant | F9: Client | G9: Montant | I9: Dépenses:Essence,Divers | L9: Montant
B10: Billetsde20 | C10: 2320 | D10: alishan rest | E10: 260.52 | F10: Till | G10: 17024.65 | I10: houcine gasoil | L10: 80
B11: Billetsde10 | C11: 1490 | F11: sancont | I11: skandar gasoil | L11: 80
B12: Billetsde5 | C12: 80 | I12: ahmed gasoil | L12: 80
B13: Monnaie | I13: samir lavage petit camion | L13: 10
B14: Total | C14: =SUM(C9:C13) -> 6240
B15: Fonddecaisse | C15: 383 | D15: Total | E15: =SUM(E10:E14) -> 260.52 | F15: Total | G15: =SUM(G10:G14) -> 17024.65 | I15: DifférenceFondCaisse | L15: =C15-'22'!C18 -> 383
K16: Total | L16: =(SUM(L10:L15))*-1 -> -633
A18: LIVRAISONS
A19: CODECLIENT | B19: PaiementsChèques | E19: Montant | F19: Banque | G19: Numero | H19: Remarques | L19: SAP
A20: C1541 | B20: Sarl Cdr | E20: 359.93 | F20: BP | G20: 6386 | L20: OK
A21: C7637 | B21: CHIKEN FRENZY | E21: 1958.21 | F21: LCL | G21: 6155360 | L21: OK
A22: C5499 | B22: LATIFA AFIF | E22: 566.04 | F22: SG | G22: 18 | L22: OK
A23: C4494 | B23: MCV Daumesnil | E23: 341.55 | F23: BRED | G23: 8622366 | L23: OK
A24: C4299 | B24: les 5 freres | E24: 521.41 | F24: BP | G24: 730 | L24: ok
A25: c1428 | B25: NOUJOUM | E25: 266.5 | F25: caisse d'epargne | G25: 2035 | L25: ok
A38: CODECLIENT | B38: PaiementsEspèces | E38: Montant | F38: Remarques | L38: SAP
A39: C7824 | B39: Polydoros Skliros | E39: 335.47 | L39: OK
A40: C5276 | B40: Silan | E40: 293.21 | L40: OK
A41: C5702 | B41: Fahad Muhammad | E41: 388.11 | L41: OK
A42: C3110 | B42: Artipain | E42: 335.47 | L42: OK
B43: EXTRA PALETTE | E43: 75 | F43: EXTRA | L43: ok
A44: c4646 | B44: extra chicken land | E44: 203.08
A48: CODECLIENT | B48: PaiementsCBSite | E48: Montant | F48: Remarques | L48: SAP
A53: CODECLIENT | B53: PaiementsCBTéléphone | E53: Montant | F53: Remarques | L53: SAP
A54: C6108 | B54: LE ROCHER | C54: 802.36 | D54: cari versailles | E54: 356.95 | L54: OK
A55: C5977 | C55: brandecision | E55: 4788.9 | L55: OK
A56: C6723 | C56: LA PETITE PAUSE | E56: 438.66 | L56: OK
A57: C5170 | C57: FARMER PARIS | E57: 2140.21 | L57: OK
A58: C7191 | C58: O'Tacos-MCL DISTRIBUTION LAUDIER Charles | E58: 538.01 | L58: OK
A59: C7191 | C59: O'Tacos-MCL DISTRIBUTION LAUDIER Charles | E59: 695.91 | L59: OK
A60: C7191 | C60: LI DISTRIBUTION | E60: 239.81 | L60: OK
A61: C6106 | C61: Keanu Gilson | E61: 4028.53 | L61: OK
A62: C6147 | C62: saint georges France | E62: 501.9 | L62: OK
A63: C7149 | C63: LES DEMEURES DE L'AUBE | E63: 200 | L63: OK
A64: C7604 | C64: maxime stefanos | E64: 713.39 | L64: OK
A65: C5705 | C65: LE PARISIEN(Mohamed Soussi) | E65: 2009.38 | L65: OK
A66: C6538 | B66: Royal food | C66: 675.28 | D66: cqfd | E66: 1525.53 | L66: OK
A67: C6555 | B67: Ahmed Bellahcene | C67: 689.72 | D67: cqfd | E67: 946.89 | L67: OK
A68: C6842 | B68: Dream pizza And pastry | C68: 340.26 | D68: new | E68: 1497.73 | L68: OK
A69: CODECLIENT | B69: Virements | E69: Montant | F69: Remarques | L69: SAP
A76: CODECLIENT | B76: Livraisonsnonpayées | E76: Montant | F76: Remarques | L76: SAP
A77: C7478 | B77: KFE Kaptain Fry | E77: 2280.11 | L77: OK
A78: C3086 | B78: Chicken Square | E78: 678.23 | L78: OK
A79: C6155 | B79: ZIG ZAG CAFE | E79: 320.54 | L79: OK
A80: C2718 | B80: LILIANE & ILIANE | E80: 673.55 | L80: OK
A81: C7336 | B81: SC ONE | E81: 1276.96 | L81: OK
A82: C7745 | B82: David Robillard | E82: 816.6 | L82: OK
A83: C4324 | B83: MARGUERITE 04 | E83: 276.05 | L83: OK
A84: C4231 | B84: Le soleil d'or | E84: 265.85 | L84: OK
A85: C6801 | B85: ilann dardour | E85: 514.84 | L85: OK
A86: C6653 | C86: BOLLYWOOD | E86: 1463.32 | L86: OK
A87: C6018 | C87: Mami Food | E87: 1767.98 | L87: OK
A88: C6395 | C88: THE KITCHEN EAT MEAT PARIS | E88: 358.4 | L88: OK
A89: C5550 | B89: Yohan SULTAN | E89: 469.82 | L89: OK
A90: C5842 | B90: garba cahud la courneuve | E90: 376.21 | L90: OK
A91: C4084 | C91: SOGEMAT | E91: 705.64 | L91: OK
A92: c7774 | C92: WABA FOOD | E92: 384.76 | L92: ok
A93: c7435 | C93: ESPACE DA | E93: 1733.79 | L93: ok
B100: TOTALESPECES | E100: =SUM(E39:E47) -> 1630.34
B101: TOTALCHEQUES | E101: =SUM(E20:E37) -> 4013.64
B102: TOTALCBInternet&Phone | E102: =SUM(E49:E68) -> 20621.8

Sheet 24
I1: DATE | J1: 46136
E3: RemiseBancaire(SAP) | G3: no 01552767 4105 | I3: EXCEL
E4: Espèces | F4: 7465 | G4: no 01552772 3360 | I4: ESPECES | K4: =E97+C14 -> 7493.09
E5: Chèques | F5: 4576.14 | G5: no 9 4576,14 | I5: CHEQUES | K5: =E15+E98 -> 4576.14
E6: Monnaienondéposée | F6: 28.09 | I6: CARTECREDIT | K6: =G15+E99 -> 20645.41
I7: VIREMENT | K7: =SUM(E59:E64) -> 0
B8: CaisseEspèces | D8: Caissechèques | F8: CaisseCB
B9: Billetsde50 | C9: 2050 | D9: Client | E9: Montant | F9: Client | G9: Montant | I9: Dépenses:Essence,Divers | L9: Montant
B10: Billetsde20 | C10: 900 | D10: alishan rest | E10: 589.67 | F10: Till | G10: 18456.89 | I10: samir gasoilet et ad blu | L10: 233
B11: Billetsde10 | C11: 1490 | D11: l'emeraude | E11: 669.02 | F11: sancont
B12: Billetsde5 | C12: 410 | D12: 3a food | E12: 213.39
B13: Monnaie
B14: Total | C14: =SUM(C9:C13) -> 4850
B15: Fonddecaisse | C15: 323 | D15: Total | E15: =SUM(E10:E14) -> 1472.08 | F15: Total | G15: =SUM(G10:G14) -> 18456.89 | I15: DifférenceFondCaisse | L15: =C15-'23'!C15 -> -60
K16: Total | L16: =(SUM(L10:L15))*-1 -> -173
A18: LIVRAISONS
A19: CODECLIENT | B19: PaiementsChèques | E19: Montant | F19: Banque | G19: Numero | H19: Remarques | L19: SAP
A20: c3476 | B20: VICTORIA 168 | E20: 697.27 | F20: sg | G20: 304 | L20: ok
A21: c5428 | B21: restaurant sakata xu | E21: 310.53 | F21: bred | G21: 7379318 | L21: ok
A22: c1919 | B22: DELICE PROVENCE 4 SAISONS | E22: 442.53 | F22: caisse d'epargne | G22: 9978479 | L22: ok
A23: c1936 | B23: LE PHENIX | E23: 313.91 | F23: ca | G23: 8328842 | L23: ok
A24: c6561 | B24: Al Matham | E24: 613.67 | F24: bp | G24: 397 | L24: ok
A25: c5397 | B25: Hussein Ibrahim | E25: 726.15 | F25: bred | G25: 8153979 | L25: ok
A38: CODECLIENT | B38: PaiementsEspèces | E38: Montant | F38: Remarques | L38: SAP
A39: c4256 | B39: JAWIDA WALA | E39: 512.62 | L39: ok
A40: c3017 | B40: PF CARDINET (MATHIEU Boulangerie) | E40: 431.22 | L40: ok
A41: c3283 | B41: Les délices de kacem | E41: 270.05 | L41: ok
A42: c5031 | B42: Georges Kfoury | E42: 617.78 | L42: ok
A43: c2605 | B43: YZ GOURMANDIZ | E43: 811.42 | L43: ok
A48: CODECLIENT | B48: PaiementsCBSite | E48: Montant | F48: Remarques | L48: SAP
B49: 25/03/2026 Paiement Express Checkout: Sylvain Apparu Terminé | E49: 1380.65 | F49: 27.86 | G49: 1352.79 | H49: paypal + cash | L49: ok
B50: 01/04/2026 Paiement DCC: Mohammed Bodrul Islam Terminé | E50: 496.42 | F50: 3.08 | G50: 493.34 | H50: paypal + cash | L50: ok
A53: CODECLIENT | B53: PaiementsCBTéléphone | E53: Montant | F53: Remarques | L53: SAP
A54: C6860 | B54: SASU HEAVY'S | C54: 802.36 | D54: cari versailles | E54: 311.45 | F54: EXTRA | L54: OK
C55: 675.28 | D55: cqfd
C56: 689.72 | D56: cqfd
C57: 340.26 | D57: new
A58: CODECLIENT | B58: Virements | E58: Montant | F58: Remarques | L58: SAP
A65: CODECLIENT | B65: Livraisonsnonpayées | E65: Montant | F65: Remarques | L65: SAP
A66: c7259 | B66: EDEN QASIMI | E66: 282.71 | L66: ok
A67: c6762 | B67: LOTUS PROVENCE | E67: 342.52 | L67: ok
A68: c6508 | B68: Rannouch Express | E68: 513.63 | L68: ok
A69: c6683 | B69: Chicken state | E69: 1487.85 | L69: ok
A70: c6767 | B70: SAUCE | E70: 307.84 | L70: OK
A71: c1513 | B71: EDENDI | E71: 4499.28 | L71: ok
A72: c5020 | B72: primo | E72: 1370.13 | L72: ok
A73: c6052 | B73: Les Turbines | E73: 252.98 | L73: ok
A74: c7488 | C74: W.T FOOD | E74: 586.62 | L74: ok
A75: c5861 | C75: CRAZY PIMENT | E75: 323.51 | L75: ok
A76: c3393 | C76: MARWAH (CHICKEN SPOT) | E76: 2600.56 | L76: ok
A77: c6860 | C77: SASU HEAVY'S | E77: 311.45 | L77: ok
A78: c3585 | C78: Sarl Burger Factory 2 | E78: 322.55 | L78: ok
A79: c7675 | B79: TOKYORAMA (O'9 POKE) | E79: 374.85 | L79: ok
A80: c6916 | C80: B.K FACTORY | E80: 926.95 | L80: ok
A81: c6199 | C81: COADRI DIFFUSION | E81: 5333.23 | L81: ok
A82: c3127 | C82: moustache et fils | E82: 1020.89 | L82: ok
A83: c7737 | C83: SARL PESNEL | E83: 822.36 | L83: ok
A84: c2886 | C84: NEHA AUBERVILLER (chicken spot) | E84: 758.06 | L84: ok
A85: c5873 | C85: Luna | E85: 303.67 | L85: ok
A86: c7259 | C86: EDEN QASIMI | E86: 252.19 | L86: ok
A87: c4994 | C87: L'ATELIER DU COUSCOUS | E87: 674.43 | L87: ok
A88: c1743 | C88: RAISA | E88: 1746.32 | L88: ok
A89: c5923 | B89: Chez PAUL | E89: 809.3 | L89: ok
B97: TOTALESPECES | E97: =SUM(E39:E47) -> 2643.09
B98: TOTALCHEQUES | E98: =SUM(E20:E37) -> 3104.06
B99: TOTALCBInternet&Phone | E99: =SUM(E49:E57) -> 2188.52

Sheet 25
I1: DATE | J1: 46137
G2: no 01552819 1730
E3: RemiseBancaire(SAP) | G3: no 01552787 2465 | I3: EXCEL
E4: Espèces | F4: 11955 | G4: no 01552804 7760 | I4: ESPECES | K4: =E80+C14 -> 11956.75
E5: Chèques | F5: 1383.68 | G5: no 3 1383,68 | I5: CHEQUES | K5: =E15+E81 -> 1383.68
E6: Monnaienondéposée | F6: 1.75 | I6: CARTECREDIT | K6: =G15+E82 -> 26970.91
I7: VIREMENT | K7: =SUM(E59:E64) -> 0
B8: CaisseEspèces | D8: Caissechèques | F8: CaisseCB
B9: Billetsde50 | C9: 6850 | D9: Client | E9: Montant | F9: Client | G9: Montant | I9: Dépenses:Essence,Divers | L9: Montant
B10: Billetsde20 | C10: 2420 | D10: zeeshan | E10: 417.29 | F10: Till | G10: 26970.91 | I10: ahmed gasoil | L10: 50
B11: Billetsde10 | C11: 2510 | D11: buffet gare | E11: 576.99 | F11: sancont
B12: Billetsde5 | C12: 130 | D12: alishan rest | E12: 389.4
B13: Monnaie
B14: Total | C14: =SUM(C9:C13) -> 11910
B15: Fonddecaisse | C15: 241 | D15: Total | E15: =SUM(E10:E14) -> 1383.68 | F15: Total | G15: =SUM(G10:G14) -> 26970.91 | I15: DifférenceFondCaisse | L15: =C15-'24'!C15 -> -82
K16: Total | L16: =(SUM(L10:L15))*-1 -> 32
A18: LIVRAISONS
A19: CODECLIENT | B19: PaiementsChèques | E19: Montant | F19: Banque | G19: Numero | H19: Remarques | L19: SAP
A38: CODECLIENT | B38: PaiementsEspèces | E38: Montant | F38: Remarques | L38: SAP
B39: extra sylhet food | E39: 46.75 | L39: ok
A48: CODECLIENT | B48: PaiementsCBSite | E48: Montant | F48: Remarques | L48: SAP
B49: extra polat 27 | F49: extra 200
A53: CODECLIENT | B53: PaiementsCBTéléphone | E53: Montant | F53: Remarques | L53: SAP
C54: 802.36 | D54: cari versailles
C55: 675.28 | D55: cqfd
C56: 689.72 | D56: cqfd
C57: 340.26 | D57: new
A58: CODECLIENT | B58: Virements | E58: Montant | F58: Remarques | L58: SAP
A65: CODECLIENT | B65: Livraisonsnonpayées | E65: Montant | F65: Remarques | L65: SAP
B80: TOTALESPECES | E80: =SUM(E39:E47) -> 46.75
B81: TOTALCHEQUES | E81: =SUM(E20:E37) -> 0
B82: TOTALCBInternet&Phone | E82: =SUM(E49:E57) -> 0

Sheet 26
I1: DATE | J1: 46138
E3: RemiseBancaire(SAP) | I3: EXCEL
E4: Espèces | I4: ESPECES | K4: =E80+C14 -> 0
E5: Chèques | I5: CHEQUES | K5: =E15+E81 -> 0
E6: Monnaienondéposée | I6: CARTECREDIT | K6: =G15+E82 -> 0
I7: VIREMENT | K7: =SUM(E59:E64) -> 0
B8: CaisseEspèces | D8: Caissechèques | F8: CaisseCB
B9: Billetsde50 | D9: Client | E9: Montant | F9: Client | G9: Montant | I9: Dépenses:Essence,Divers | L9: Montant
B10: Billetsde20 | F10: Till
B11: Billetsde10 | F11: sancont
B12: Billetsde5
B13: Monnaie
B14: Total | C14: =SUM(C9:C13) -> 0
B15: Fonddecaisse | D15: Total | E15: =SUM(E10:E14) -> 0 | F15: Total | G15: =SUM(G10:G14) -> 0 | I15: DifférenceFondCaisse | L15: =C15-'25'!C15 -> -241
K16: Total | L16: =(SUM(L10:L15))*-1 -> 241
A18: LIVRAISONS
A19: CODECLIENT | B19: PaiementsChèques | E19: Montant | F19: Banque | G19: Numero | H19: Remarques | L19: SAP
A38: CODECLIENT | B38: PaiementsEspèces | E38: Montant | F38: Remarques | L38: SAP
A48: CODECLIENT | B48: PaiementsCBSite | E48: Montant | F48: Remarques | L48: SAP
A53: CODECLIENT | B53: PaiementsCBTéléphone | E53: Montant | F53: Remarques | L53: SAP
C54: 802.36 | D54: cari versailles
C55: 675.28 | D55: cqfd
C56: 689.72 | D56: cqfd
C57: 340.26 | D57: new
A58: CODECLIENT | B58: Virements | E58: Montant | F58: Remarques | L58: SAP
A65: CODECLIENT | B65: Livraisonsnonpayées | E65: Montant | F65: Remarques | L65: SAP
B80: TOTALESPECES | E80: =SUM(E39:E47) -> 0
B81: TOTALCHEQUES | E81: =SUM(E20:E37) -> 0
B82: TOTALCBInternet&Phone | E82: =SUM(E49:E57) -> 0

Sheet 27
I1: DATE | J1: 46139
E3: RemiseBancaire(SAP) | G3: NO 01552824 5550 | I3: EXCEL
E4: Espèces | F4: 7840 | G4: NO 00279925 2290 | I4: ESPECES | K4: =E94+C14 -> 7841.56
E5: Chèques | F5: 5694.5 | G5: NO 12 5694,50 | I5: CHEQUES | K5: =E15+E95 -> 5694.5
E6: Monnaienondéposée | F6: 1.56 | I6: CARTECREDIT | K6: =G15+E96 -> 23461.53
I7: VIREMENT | K7: =SUM(E65:E70) -> 0
B8: CaisseEspèces | D8: Caissechèques | F8: CaisseCB
B9: Billetsde50 | C9: 2550 | D9: Client | E9: Montant | F9: Client | G9: Montant | I9: Dépenses:Essence,Divers | L9: Montant
B10: Billetsde20 | C10: 1520 | D10: AU SUN DINE | E10: 832.8 | F10: Till | G10: 19873.58 | I10: ABOUBAKER gasoil | L10: 100
B11: Billetsde10 | C11: 3620 | D11: MAX CHICKEN | E11: 814.09 | F11: sancont | I11: SAMIR GASOIL PL | L11: 200
B12: Billetsde5 | C12: 90 | D12: ALISHAN REST | E12: 435.88 | I12: SIKANDAR GASOIL | L12: 80
B13: Monnaie | D13: ZEESHAN | E13: 377.09 | I13: AMOR GASOIL | L13: 100
B14: Total | C14: =SUM(C9:C13) -> 7780 | I14: SAMIR LAVAGE PL | L14: 50
B15: Fonddecaisse | C15: 680 | D15: Total | E15: =SUM(E10:E14) -> 2459.86 | F15: Total | G15: =SUM(G10:G14) -> 19873.58 | I15: DifférenceFondCaisse | L15: =C15-'26'!C15 -> 680
K16: Total | L16: =(SUM(L10:L15))*-1 -> -1210
A18: LIVRAISONS
A19: CODECLIENT | B19: PaiementsChèques | E19: Montant | F19: Banque | G19: Numero | H19: Remarques | L19: SAP
A20: c1886 | B20: LE CHINOIS GOURMET | E20: 307.76 | F20: lcl | G20: 6745842 | L20: ok
A21: c4492 | B21: MARMARIS | E21: 437.56 | F21: cic | G21: 3910451 | L21: ok
A22: c4602 | B22: chamas tacos guerrida | E22: 709.16 | F22: cic | G22: 3885378 | L22: ok
A23: c3476 | B23: VICTORIA 168 | E23: 413.19 | F23: sg | G23: 305 | L23: ok
A24: c6881 | B24: La pyramide | E24: 381.27 | F24: lcl | G24: 2232940 | L24: ok
A25: c6940 | B25: MCV LA VILLETTE | E25: 501.22 | F25: sg | G25: 79 | L25: ok
A26: c4204 | B26: Kashmir express | E26: 213.34 | F26: lcl | G26: 2722689 | L26: ok
A27: c6103 | B27: Monir Hossain | E27: 271.14 | F27: bnp | G27: 6127552 | L27: ok
A38: CODECLIENT | B38: PaiementsEspèces | E38: Montant | F38: Remarques | L38: SAP
B39: SAMIR RETOUR | E39: 50 | F39: RETOUR LAVAGE
B40: RETOUR ABOUBAKER | E40: 11.56 | F40: RETOUR REDUCTION GASOIL
A48: CODECLIENT | B48: PaiementsCBSite | E48: Montant | F48: Remarques | L48: SAP
A49: C2718 | B49: LILIANE & ILIANE | E49: 367.75 | L49: OK
A50: C2718 | C50: LILIANE & ILIANE | E50: 673.55 | L50: OK
A51: C7259 | C51: EDEN QASIMI | E51: 180.84 | L51: OK
A52: C7259 | C52: EDEN QASIMI | E52: 282.71 | L52: OK
A53: C7259 | C53: EDEN QASIMI | E53: 215.28 | L53: OK
A54: C7737 | C54: SARL PESNEL | E54: 918.29 | L54: OK
A55: C4994 | C55: L'ATELIER DU COUSCOUS | E55: 540.75 | L55: OK
A56: C1403 | B56: SARL GOKAL | E56: 408.78 | L56: OK
A59: CODECLIENT | B59: PaiementsCBTéléphone | E59: Montant | F59: Remarques | L59: SAP
C60: 802.36 | D60: cari versailles
C61: 675.28 | D61: cqfd
C62: 689.72 | D62: cqfd
C63: 340.26 | D63: new
A64: CODECLIENT | B64: Virements | E64: Montant | F64: Remarques | L64: SAP
A71: CODECLIENT | B71: Livraisonsnonpayées | E71: Montant | F71: Remarques | L71: SAP
A72: c4368 | B72: Restaurant Van April | E72: 407.37 | L72: ok
A73: C7336 | B73: SC ONE | E73: 785.04 | L73: OK
A74: C6802 | B74: Torab Maroof | E74: 782.24 | L74: OK
A75: c6268 | B75: SUSHI KEKKOO HAOBO XU | E75: 437.5 | L75: ok
A76: c1403 | B76: SARL GOKAL | E76: 408.78 | L76: ok
A77: c1838 | C77: KAB'HOUSE BETA FOOD | E77: 531.96 | L77: ok
A78: c6018 | C78: Mami Food | E78: 2603.15 | L78: ok
A79: c7621 | C79: COVA SERVICES | E79: 316.44 | L79: ok
A80: c6345 | C80: La Volaille Express | E80: 675.53 | L80: ok
A81: c1465 | C81: DELICE DE BEYROUTH IHLIBAN | E81: 660.19 | L81: ok
A82: c4470 | C82: TABAC DU PALAIS - SOUVENIRS ET SERVICE | E82: 311.97 | L82: ok
A83: c6018 | C83: Mami Food | E83: 1912.67 | L83: ok
A84: c3287 | C84: BUDDIE'S | E84: 388.42 | L84: ok
A85: c5550 | B85: Yohan SULTAN | E85: 586.94 | L85: ok
A86: C7838 | B86: AZ METAL | E86: 28801.5 | L86: OK
A87: C1732 | B87: sarl fried chicken | E87: 413.47 | L87: OK
A88: C2729 | B88: SANA | E88: 1416.46
B94: TOTALESPECES | E94: =SUM(E39:E47) -> 61.56
B95: TOTALCHEQUES | E95: =SUM(E20:E37) -> 3234.64
B96: TOTALCBInternet&Phone | E96: =SUM(E49:E63) -> 3587.95

Sheet 28
I1: DATE | J1: 46140
E3: RemiseBancaire(SAP) | G3: no 05074666 10000 | I3: EXCEL
E4: Espèces | F4: 15180 | G4: no 050774651 5180 | I4: ESPECES | K4: =E230+C14 -> 15197.42
E5: Chèques | F5: 7431.58 | G5: no 10 7431,58 | I5: CHEQUES | K5: =E15+E231 -> 7431.58
E6: Monnaienondéposée | F6: 17.42 | I6: CARTECREDIT | K6: =G15+E232 -> 24026.59
I7: VIREMENT | K7: =SUM(E64:E207) -> 251048.82
B8: CaisseEspèces | D8: Caissechèques | F8: CaisseCB
B9: Billetsde50 | C9: 1500 | D9: Client | E9: Montant | F9: Client | G9: Montant | I9: Dépenses:Essence,Divers | L9: Montant
B10: Billetsde20 | C10: 1380 | D10: delta | E10: 3250.78 | F10: Till | G10: 18206.48 | I10: ahmed | L10: 80
B11: Billetsde10 | C11: 650 | D11: alishan rest | E11: 355.25 | F11: sancont | I11: reaparation hayon | L11: 80
B12: Billetsde5 | C12: 50 | I12: ahmed peage | L12: 8
B13: Monnaie | I13: abu bakar leroy merlin | L13: 196.8
B14: Total | C14: =SUM(C9:C13) -> 3580
B15: Fonddecaisse | C15: 638 | D15: Total | E15: =SUM(E10:E14) -> 3606.03 | F15: Total | G15: =SUM(G10:G14) -> 18206.48 | I15: DifférenceFondCaisse | L15: =C15-'27'!C15 -> -42
K16: Total | L16: =(SUM(L10:L15))*-1 -> -322.8
A18: LIVRAISONS
A19: CODECLIENT | B19: PaiementsChèques | E19: Montant | F19: Banque | G19: Numero | H19: Remarques | L19: SAP
A20: c6940 | B20: MCV LA VILLETTE | E20: 261.42 | F20: sg | G20: 80 | L20: ok
A21: c3476 | B21: VICTORIA 168 | E21: 583.47 | F21: sg | G21: 306 | L21: ok
A22: c5205 | B22: restaurant yoshi world | E22: 346.61 | F22: caisse d'epargne | G22: 715 | L22: ok
A23: c6470 | B23: Rannouch | E23: 267.7 | F23: bnp | G23: 1681132 | L23: ok
A24: c6616 | B24: SIRIUS | E24: 566.82 | F24: cic | G24: 4170216 | L24: ok
A25: c2987 | B25: boulangerie les poètes | E25: 823.67 | F25: caisse d'pargne | G25: 698 | L25: ok
A26: c5004 | B26: Robert Asseraf | E26: 634.67 | F26: sg | G26: 894 | L26: ok
A27: c5316 | B27: pizzeria vivaldi | E27: 341.19 | F27: bnp | G27: 1946182 | L27: ok
A38: CODECLIENT | B38: PaiementsEspèces | E38: Montant | F38: Remarques | L38: SAP
A39: c6900 | B39: Sabbir Ramjan hossain | E39: 671.41 | L39: ok
A40: c5702 | B40: Fahad Muhammad | E40: 403.43 | L40: ok
A41: c4031 | B41: LE WARNER | E41: 236.41 | L41: ok
A42: c2431 | B42: ARGENSON ET SEPT ARPENTS | E42: 306.17 | L42: ok
A43: c6273 | B43: jk distribution | E43: 10000 | L43: ok
A48: CODECLIENT | B48: PaiementsCBSite | E48: Montant | F48: Remarques | L48: SAP
B49: 20/04/2026 Paiement DCC: FARID BOUDIHAR Terminé | E49: =SUM(F49+G49) -> 1376.03 | F49: 1367.67 | G49: 8.36 | H49: PAYPAL + CASH | L49: OK
B50: 20/04/2026 Paiement DCC: Sodary KHAMPRASEUTH Terminé | E50: =SUM(F50+G50) -> 458.85 | F50: 456 | G50: 2.85 | H50: PAYPAL + CASH | L50: OK
B51: 20/04/2026 Paiement DCC: lassaad ben daali Terminé | E51: =SUM(F51+G51) -> 553.58 | F51: 550.16 | G51: 3.42 | H51: PAYPAL + CASH | L51: OK
B52: 21/04/2026 Paiement DCC: Werner Meunier Terminé | E52: =SUM(F52+G52) -> 1376.63 | F52: 1368.27 | G52: 8.36 | H52: PAYPAL + CASH | L52: OK
B53: 21/04/2026 Paiement DCC: Adbus Shahid Muhammed Terminé | E53: =SUM(F53+G53) -> 419.01 | F53: 416.4 | G53: 2.61 | H53: PAYPAL + CASH | L53: OK
B54: 21/04/2026 Paiement DCC: SANDRINE QUEVILLON Terminé | E54: =SUM(F54+G54) -> 490.69 | F54: 487.65 | G54: 3.04 | H54: PAYPAL + CASH | L54: OK
B55: 21/04/2026 Paiement DCC: Uthayaveni Sivananthan Terminé | E55: =SUM(F55+G55) -> 462.75 | F55: 459.87 | G55: 2.88 | H55: PAYPAL + CASH | L55: OK
B56: 21/04/2026 Paiement DCC: frederic gicquel Terminé | E56: =SUM(F56+G56) -> 324.17 | F56: 322.12 | G56: 2.05 | H56: PAYPAL + CASH | L56: OK
B57: 22/04/2026 Paiement Express Checkout: akram chammam Terminé | E57: =SUM(F57+G57) -> 358.4 | F57: 350.98 | G57: 7.42 | H57: PAYPAL + CASH | L57: OK
A58: CODECLIENT | B58: PaiementsCBTéléphone | E58: Montant | F58: Remarques | L58: SAP
C59: 802.36 | D59: cari versailles
C60: 675.28 | D60: cqfd
C61: 689.72 | D61: cqfd
C62: 340.26 | D62: new
A63: CODECLIENT | B63: Virements | E63: Montant | F63: Remarques | L63: SAP
A64: C3964 | B64: HAOCH LI | E64: 595.4 | L64: OK
A65: C5232 | B65: LES SAVEURS DU MONDE LA PAILLOTE | E65: 83.25 | L65: OK
A66: C5232 | B66: LES SAVEURS DU MONDE LA PAILLOTE | E66: 1529.79 | L66: OK
A67: C5170 | B67: MAMAZINI | E67: 1456.55 | L67: OK
A68: C6243 | B68: 16PARCROYALSARL | E68: 1711.67 | L68: OK
A69: c5624 | B69: MONSIEURBENRHOUMAMOHAMED | E69: 1000 | L69: OK
A70: c7116 | B70: JUINDIS | E70: 492.12 | L70: OK
A71: c5486 | B71: S.A.R.L.STOREASIE | E71: 567.54 | L71: OK
A72: c7473 | B72: MELAS | E72: 474.49 | L72: OK
A73: c7499 | B73: SASCFCCORNERSFOODCOURT | E73: 2138.49 | L73: OK
A74: c7264 | B74: LEOMINATCHY | E74: 123 | L74: OK
A75: c7671 | B75: SASAMA | E75: 746.13 | L75: OK
... A83: c7777 | B83: MRAHMEDSHAMIM | E83: 329.96 | L83: OK
B84: RANY | E84: 400.94 | L84: OK
B85: CHICKEN ASIA | E85: 581.4 | L85: OK
B86: KEVIN | E86: 259.5 | L86: OK
B87: ATS | E87: 407.37 | L87: OK
B88: SUSHIKEKKOO | E88: 437.5 | L88: OK
B89: SCONE | E89: 785.04 | L89: OK
B90: AZMETAL | E90: 28801.5 | L90: OK
B91: LACREPESURMESURE | E91: 611.8 | L91: OK
B92: FIZAN | E92: 839.34 | L92: OK
B93: GOWOK | E93: 2362.22 | L93: OK
B94: HOZCOUSCOUS | E94: 480.63 | L94: OK
B95: ESPACEDASARL | E95: 2582.79 | L95: OK
... B204: GOWOK | E204: 2026.74 | L204: OK
B205: S.A.S. CHEZ NINOU FAST FOOD | C205: S.A.S. CHEZ NINOU FAST FOOD | D205: S.A.S. CHEZ NINOU FAST FOOD | E205: 263.11 | F205: bordeaux | L205: OK
B206: S.A.S. DJURDJURA DISTRIBUTION | C206: S.A.S. DJURDJURA DISTRIBUTION | D206: S.A.S. DJURDJURA DISTRIBUTION | E206: 1479.85 | F206: bordeaux | L206: OK
B207: TRANSPORTBACOS97 | E207: 15626.56 | L207: OK
A208: CODECLIENT | B208: Livraisonsnonpayées | E208: Montant | F208: Remarques | L208: SAP
A209: c7692 | B209: SANDRINE QUEVILLON | E209: 531.38 | L209: ok
A210: c7634 | B210: Wok Factory | E210: 1203.77 | L210: ok
A211: c7811 | B211: TOKYORAMA (O'9 POKE) | E211: 316.29 | L211: ok
A212: c6383 | B212: PL | E212: 1060.49 | L212: ok
A213: c4800 | B213: SHAMEEM (Chicken spot) | E213: 1340.84 | L213: ok
A214: c4809 | B214: Akbar Khan | E214: 420.36 | L214: ok
A215: c6683 | C215: Chicken state | E215: 2184.04 | L215: ok
A216: c7728 | C216: LYDIA FOOD | E216: 310.82 | L216: ok
A217: c4168 | C217: restaurant k- chimaek | E217: 284.7 | L217: ok
A218: c7505 | C218: WAJIH HAMMOUD | E218: 343.58 | L218: ok
A219: c7336 | C219: SC ONE | E219: 882.31 | L219: ok
A220: c3938 | C220: SPICE'N'GRILL Restaurant Hala | E220: 993.04 | L220: ok
A221: c1581 | C221: PLANETE DA | E221: 4871.95 | L221: ok
A222: c7100 | B222: LE KINKS | E222: 2602.72 | L222: ok
A223: c7851 | B223: Yummy Yummy | E223: 817.34 | L223: ok
A224: c7843 | B224: SLIMANI MOHAMMED | E224: 389.95
B230: TOTALESPECES | E230: =SUM(E39:E47) -> 11617.42
B231: TOTALCHEQUES | E231: =SUM(E20:E37) -> 3825.55
B232: TOTALCBInternet&Phone | E232: =SUM(E49:E62) -> 5820.11

Sheet 29
I1: DATE | J1: 46141
E3: RemiseBancaire(SAP) | G3: NO 05074631 3615 | I3: EXCEL
E4: Espèces | F4: 6180 | G4: NO 05074646 2565 | I4: ESPECES | K4: =E97+C14 -> 6191.66
E5: Chèques | F5: 1869.94 | G5: NO 4 1869,94 | I5: CHEQUES | K5: =E15+E98 -> 1869.94
E6: Monnaienondéposée | F6: 11.66 | I6: CARTECREDIT | K6: =G15+E99 -> 30228.66
I7: VIREMENT | K7: =SUM(E61:E66) -> 23715.33
B8: CaisseEspèces | D8: Caissechèques | F8: CaisseCB
B9: Billetsde50 | D9: Client | E9: Montant | F9: Client | G9: Montant | I9: Dépenses:Essence,Divers | L9: Montant
B10: Billetsde20 | C10: 2460 | D10: ZEESHAN | E10: 799.29 | F10: Till | G10: 18249.53 | I10: AHMED | L10: 100
B11: Billetsde10 | C11: 1480 | F11: sancont | I11: SAMIR | L11: 80
B12: Billetsde5 | C12: 105 | I12: NADIA ET ZOHAIR SALARY | L12: 1440
B13: Monnaie | I13: MME ISSANE POUR BOUCHERI | L13: 119.18
B14: Total | C14: =SUM(C9:C13) -> 4045
B15: Fonddecaisse | C15: 637 | D15: Total | E15: =SUM(E10:E14) -> 799.29 | F15: Total | G15: =SUM(G10:G14) -> 18249.53 | I15: DifférenceFondCaisse | L15: =C15-'28'!C15 -> -1
K16: Total | L16: =(SUM(L10:L15))*-1 -> -1738.18
A18: LIVRAISONS
A19: CODECLIENT | B19: PaiementsChèques | E19: Montant | F19: Banque | G19: Numero | H19: Remarques | L19: SAP
A20: c5538 | B20: ZHONGJIE XIA | E20: 319.87 | F20: lcl | G20: 7738612 | L20: ok
A21: C5144 | B21: MCV FAIDHERBE | E21: 512.81 | F21: BRED | G21: 7051125 | L21: OK
A22: C5776 | B22: Haochi LI | E22: 237.97 | F22: BNP | G22: 8783657 | L22: OK
A38: CODECLIENT | B38: PaiementsEspèces | E38: Montant | F38: Remarques | L38: SAP
A39: C6171 | B39: Sarl TAMASINI | E39: 813.69 | L39: OK
A40: C9999 | B40: vente comptoir sur place | E40: 916.86 | F40: CROUSTY FAMILY | L40: OK
A41: C3788 | B41: Sylhet Food | E41: 416.11 | L41: OK
A48: CODECLIENT | B48: PaiementsCBSite | E48: Montant | F48: Remarques | L48: SAP
A49: C5977 | B49: brandecision | E49: 3014.56 | L49: OK
A50: C7843 | B50: SLIMANI MOHAMMED | E50: 389.95 | L50: OK
A51: C3287 | C51: BUDDIE'S | E51: 986.23 | L51: OK
A52: C6702 | C52: MY TACOS | E52: 1450.36 | L52: OK
A53: C7026 | B53: CRÈME FRENCH TACOS LIMITED | E53: 2357.25 | L53: OK
A54: C5977 | B54: brandecision | E54: 3780.78 | L54: OK
A55: CODECLIENT | B55: PaiementsCBTéléphone | E55: Montant | F55: Remarques | L55: SAP
C56: 802.36 | D56: cari versailles
C57: 675.28 | D57: cqfd
C58: 689.72 | D58: cqfd
C59: 340.26 | D59: new
A60: CODECLIENT | B60: Virements | E60: Montant | F60: Remarques | L60: SAP
B61: TREFLE | E61: 4043.29 | L61: OK
B62: TREFLE | E62: 16397.23 | L62: OK
B63: MNH | E63: 3274.81 | L63: OK
A67: CODECLIENT | B67: Livraisonsnonpayées | E67: Montant | F67: Remarques | L67: SAP
A68: C6939 | B68: CROUSTY CHICKEN FOOD | E68: 316.45 | L68: OK
A69: C7687 | B69: O'FRESH MARKET | E69: 6922.94 | L69: OK
A70: C7550 | B70: AQUAGO | E70: 1627.28 | L70: OK
A71: C7430 | B71: COIN CAFE | E71: 3779.53 | L71: OK
A72: C5232 | B72: Mina Chahchah Arnaud | E72: 1613.04 | L72: OK
A73: C4927 | B73: Pizzeria Sarda | E73: 2637.79 | L73: OK
A74: C1617 | B74: ASA | E74: 9043.67 | L74: OK
A75: C6645 | B75: EAT CORNER | E75: 1196.7 | L75: OK
A76: C6645 | B76: EAT CORNER | E76: 218.22 | L76: OK
A77: C5664 | B77: FOURQUET'S FRITE D'OR | E77: 2146.82 | L77: OK
A78: c6459 | C78: Fatima Khalil | E78: 337.23 | L78: ok
A79: c7336 | C79: SC ONE | E79: 840.28 | L79: ok
A80: c4368 | C80: Restaurant Van April | E80: 371.8 | L80: ok
A81: c5085 | C81: Jadak | E81: 502.14 | L81: ok
A82: c2718 | C82: LILIANE & ILIANE | E82: 497.91 | L82: ok
A83: c3127 | C83: moustache et fils | E83: 898.96 | L83: ok
A84: c4523 | C84: NEHA ST DENIS (chicken spot) | E84: 679.75 | L84: ok
A85: c7802 | C85: HCOMMERCIAL | E85: 2173.16 | L85: ok
A86: c5842 | C86: garba chaud la courneuve | E86: 314.05 | L86: ok
A87: c4357 | B87: BURGERISTE | E87: 426.14 | L87: ok
A88: C6294 | C88: CROUSTY FAMILY | E88: 1491.27 | L88: OK
A89: C5837 | C89: El Mahi Restaurant | E89: 1845.38 | L89: OK
A90: C7191 | C90: O'Tacos-MCL DISTRIBUTION | E90: 516.34 | L90: OK
A91: C4494 | C91: MCV Daumesnil | E91: 294.63 | L91: OK
A92: C6767 | C92: SAUCE | E92: 428 | L92: OK
A93: C6471 | C93: Mozzafiato Paris | E93: 273.61 | L93: OK
A94: C5540 | B94: TACO MESA | E94: 317.88 | L94: OK
A95: C5977 | B95: brandecision | E95: 3780.78 | L95: OK
B97: TOTALESPECES | E97: =SUM(E39:E47) -> 2146.66
B98: TOTALCHEQUES | E98: =SUM(E20:E37) -> 1070.65
B99: TOTALCBInternet&Phone | E99: =SUM(E49:E59) -> 11979.13

Sheet 30
I1: DATE | J1: 46142
E3: RemiseBancaire(SAP) | G3: no 05074626 2050 | I3: EXCEL
E4: Espèces | F4: 6920 | G4: no 05074611 4870 | I4: ESPECES | K4: =E87+C14 -> 6924.46
E5: Chèques | F5: 5901.45 | G5: no 12 5901,45 | I5: CHEQUES | K5: =E15+E88 -> 5901.45
E6: Monnaienondéposée | F6: 4.46 | I6: CARTECREDIT | K6: =G15+E89 -> 17128.33
I7: VIREMENT | K7: =SUM(E59:E64) -> 0
B8: CaisseEspèces | D8: Caissechèques | F8: CaisseCB
B9: Billetsde50 | C9: 2950 | D9: Client | E9: Montant | F9: Client | G9: Montant | I9: Dépenses:Essence,Divers | L9: Montant
B10: Billetsde20 | C10: 1920 | D10: l'emeraude | E10: 719.42 | F10: Till | G10: 17128.33 | I10: ahmed gasoil | L10: 240
B11: Billetsde10 | C11: 870 | D11: alishan rest | E11: 412.86 | F11: sancont | I11: samir gasoil | L11: 140
B12: Billetsde5 | D12: au sun dine | E12: 283.01 | I12: skander gasoil | L12: 70
B13: Monnaie | I13: abu bakar gasoil livraison vamion 053 | L13: 50
B14: Total | C14: =SUM(C9:C13) -> 5740 | I14: transpoerter travaux et peinture | L14: 477.32
B15: Fonddecaisse | C15: 611 | D15: Total | E15: =SUM(E10:E14) -> 1415.29 | F15: Total | G15: =SUM(G10:G14) -> 17128.33 | I15: DifférenceFondCaisse | L15: =C15-'29'!C15 -> -26
K16: Total | L16: =(SUM(L10:L15))*-1 -> -951.32
A18: LIVRAISONS
A19: CODECLIENT | B19: PaiementsChèques | E19: Montant | F19: Banque | G19: Numero | H19: Remarques | L19: SAP
A20: c5435 | B20: Massis | E20: 940.8 | F20: sg | G20: 154 | L20: ok
A21: c4602 | B21: chamas tacos guerrida | E21: 557.4 | F21: cic | G21: 33885379 | L21: ok
A22: c5161 | B22: K-CHI | E22: 257.23 | F22: bnp | G22: 9427208 | L22: ok
A23: c7597 | B23: SARKER | E23: 330.4 | F23: sg | G23: 8 | L23: ok
A24: c6508 | B24: Rannouch Express | E24: 506.27 | F24: bnp | G24: 8704972 | L24: ok
A25: c6508 | B25: Rannouch Express | E25: 513.63 | F25: bnp | G25: 8704971 | L25: ok
A26: c6940 | B26: MCV LA VILLETTE | E26: 473.93 | F26: sg | G26: 81 | L26: ok
A27: c7664 | B27: Restaurant Cheezy | E27: 633 | F27: bnp | G27: 2693025 | L27: ok
A28: c4204 | B28: Kashmir express | E28: 273.5 | F28: lcl | G28: 2722690 | L28: ok
A38: CODECLIENT | B38: PaiementsEspèces | E38: Montant | F38: Remarques | L38: SAP
A39: c4256 | B39: JAWIDA WALA | E39: 700.57 | L39: ok
A40: c7821 | B40: Adbus Shahid Muhammed | E40: 363.89 | L40: ok
B41: ahmed | E41: 120 | F41: retour gasoil
A48: CODECLIENT | B48: PaiementsCBSite | E48: Montant | F48: Remarques | L48: SAP
B49: extra vanitha pizzasur | F49: 236.35
A53: CODECLIENT | B53: PaiementsCBTéléphone | E53: Montant | F53: Remarques | L53: SAP
C54: 802.36 | D54: cari versailles
C55: 675.28 | D55: cqfd
C56: 689.72 | D56: cqfd
C57: 340.26 | D57: new
A58: CODECLIENT | B58: Virements | E58: Montant | F58: Remarques | L58: SAP
A65: CODECLIENT | B65: Livraisonsnonpayées | E65: Montant | F65: Remarques | L65: SAP
A66: c6606 | B66: MIKUNA EVENTS | E66: 801.8 | L66: ok
A67: c7767 | B67: JANNAT BD | E67: 537.02 | L67: ok
A68: c6830 | B68: Pierre-Alexandre Entraygues | E68: 360.03 | L68: ok
A69: c4379 | B69: SUKISOBA | E69: 413.26 | L69: ok
A70: c3455 | B70: THE BEAN PROJECT PARIS | E70: 263.87 | L70: ok
A71: c1681 | B71: A LA FOLIE PARIS | E71: 516.52 | L71: ok
A72: c5977 | C72: brandecision | E72: 3014.56 | L72: ok
A73: c6198 | C73: ASIAN FOOD LAB Entreprise | E73: 303.53 | L73: ok
A74: c6560 | C74: jad al rayes | E74: 329.73 | L74: ok
A75: c6018 | C75: Mami Food | E75: 2217.34 | L75: ok
A76: c7742 | C76: O'GARDEN | E76: 323.35 | L76: ok
A77: c6683 | C77: Chicken state | E77: 1209.85 | L77: ok
A78: c1581 | C78: PLANETE DA | E78: 2782.88 | L78: ok
A79: c5988 | B79: NSEDA | E79: 1411.27 | L79: ok
A80: c2820 | B80: sarl enes | E80: 681.12 | L80: ok
B87: TOTALESPECES | E87: =SUM(E39:E47) -> 1184.46
B88: TOTALCHEQUES | E88: =SUM(E20:E37) -> 4486.16
B89: TOTALCBInternet&Phone | E89: =SUM(E49:E57) -> 0

Sheet 31
I1: DATE | J1: 31/04/2026
E3: RemiseBancaire(SAP) | I3: EXCEL
E4: Espèces | I4: ESPECES | K4: =E80+C14 -> 0
E5: Chèques | I5: CHEQUES | K5: =E15+E81 -> 0
E6: Monnaienondéposée | I6: CARTECREDIT | K6: =G15+E82 -> 0
I7: VIREMENT | K7: =SUM(E59:E64) -> 0
B8: CaisseEspèces | D8: Caissechèques | F8: CaisseCB
B9: Billetsde50 | D9: Client | E9: Montant | F9: Client | G9: Montant | I9: Dépenses:Essence,Divers | L9: Montant
B10: Billetsde20 | F10: Till
B11: Billetsde10 | F11: sancont
B12: Billetsde5
B13: Monnaie
B14: Total | C14: =SUM(C9:C13) -> 0
B15: Fonddecaisse | D15: Total | E15: =SUM(E10:E14) -> 0 | F15: Total | G15: =SUM(G10:G14) -> 0 | I15: DifférenceFondCaisse | L15: =C15-'30'!C15 -> -611
K16: Total | L16: =(SUM(L10:L15))*-1 -> 611
A18: LIVRAISONS
A19: CODECLIENT | B19: PaiementsChèques | E19: Montant | F19: Banque | G19: Numero | H19: Remarques | L19: SAP
A38: CODECLIENT | B38: PaiementsEspèces | E38: Montant | F38: Remarques | L38: SAP
A48: CODECLIENT | B48: PaiementsCBSite | E48: Montant | F48: Remarques | L48: SAP
A53: CODECLIENT | B53: PaiementsCBTéléphone | E53: Montant | F53: Remarques | L53: SAP
C54: 802.36 | D54: cari versailles
C55: 675.28 | D55: cqfd
C56: 689.72 | D56: cqfd
C57: 340.26 | D57: new
A58: CODECLIENT | B58: Virements | E58: Montant | F58: Remarques | L58: SAP
A65: CODECLIENT | B65: Livraisonsnonpayées | E65: Montant | F65: Remarques | L65: SAP
B80: TOTALESPECES | E80: =SUM(E39:E47) -> 0
B81: TOTALCHEQUES | E81: =SUM(E20:E37) -> 0
B82: TOTALCBInternet&Phone | E82: =SUM(E49:E57) -> 0

Sheet TOTAL
A1: TOTAL
A2: DATE | B2: ESPECE | C2: CHEQUE | D2: VIREMENT | E2: cb | F2: depense | G2: total
A3: 46113 | B3: =SUM(TOTAL!J4:K4) -> 0 | C3: =SUM(#REF!) -> #REF! | D3: =SUM(#REF!) -> #REF! | E3: =SUM(#REF!) -> #REF! | F3: =#REF! -> #REF! | G3: =SUM(B3:E3)-F3 -> #REF!
A4: 46116 | B4: =SUM(TOTAL!J5:K5) -> 0 | C4: =SUM(#REF!) -> #REF! | D4: =SUM(#REF!) -> #REF! | E4: =SUM(#REF!) -> #REF! | F4: =#REF! -> #REF! | G4: =SUM(B4:E4)-F4 -> #REF!
A5: 46116 | B5: =SUM(TOTAL!J6:K6) -> 0 | C5: =SUM(#REF!) -> #REF! | D5: =SUM(#REF!) -> #REF! | E5: =SUM(#REF!) -> #REF! | F5: =#REF! -> #REF! | G5: =SUM(B5:E5)-F5 -> #REF!
A6: 46116 | B6: =SUM(TOTAL!J7:K7) -> 0 | C6: =SUM(#REF!) -> #REF! | D6: =SUM(#REF!) -> #REF! | E6: =SUM(#REF!) -> #REF! | F6: =#REF! -> #REF! | G6: =SUM(B6:E6)-F6 -> #REF!
A7: 46117 | B7: =SUM(TOTAL!J8:K8) -> 0 | C7: =SUM(#REF!) -> #REF! | D7: =SUM(#REF!) -> #REF! | E7: =SUM(#REF!) -> #REF! | F7: =#REF! -> #REF! | G7: =SUM(B7:E7)-F7 -> #REF!
A8: 46118 | B8: =SUM(TOTAL!J9:K9) -> 0 | C8: =SUM(#REF!) -> #REF! | D8: =SUM(#REF!) -> #REF! | E8: =SUM(#REF!) -> #REF! | F8: =#REF! -> #REF! | G8: =SUM(B8:E8)-F8 -> #REF!
A9: 46119 | B9: =SUM(TOTAL!J10:K10) -> 0 | C9: =SUM(#REF!) -> #REF! | D9: =SUM(#REF!) -> #REF! | E9: =SUM(#REF!) -> #REF! | F9: =#REF! -> #REF! | G9: =SUM(B9:E9)-F9 -> #REF!
A10: 46120 | B10: =SUM(TOTAL!J2:K2) -> 0 | C10: =SUM(#REF!) -> #REF! | D10: =SUM(#REF!) -> #REF! | E10: =SUM(#REF!) -> #REF! | F10: =#REF! -> #REF! | G10: =SUM(B10:E10)-F10 -> #REF!
A11: 46121 | B11: =SUM(TOTAL!J12:K12) -> 0 | C11: =SUM(#REF!) -> #REF! | D11: =SUM(#REF!) -> #REF! | E11: =SUM(#REF!) -> #REF! | F11: =#REF! -> #REF! | G11: =SUM(B2:E2)-F2 -> #VALUE!
A12: 46122 | B12: =SUM(TOTAL!J13:K13) -> 0 | C12: =SUM(#REF!) -> #REF! | D12: =SUM(#REF!) -> #REF! | E12: =SUM(#REF!) -> #REF! | F12: =#REF! -> #REF! | G12: =SUM(B12:E12)-F12 -> #REF!
A13: 46123 | B13: =SUM(TOTAL!J14:K14) -> 0 | C13: =SUM(#REF!) -> #REF! | D13: =SUM(#REF!) -> #REF! | E13: =SUM(#REF!) -> #REF! | F13: =#REF! -> #REF! | G13: =SUM(B13:E13)-F13 -> #REF!
A14: 46124 | B14: =SUM(TOTAL!J15:K15) -> 0 | C14: =SUM(#REF!) -> #REF! | D14: =SUM(#REF!) -> #REF! | E14: =SUM(#REF!) -> #REF! | F14: =#REF! -> #REF! | G14: =SUM(B14:E14)-F14 -> #REF!
A15: 46125 | B15: =SUM(TOTAL!J16:K16) -> 0 | C15: =SUM(#REF!) -> #REF! | D15: =SUM(#REF!) -> #REF! | E15: =SUM(#REF!) -> #REF! | F15: =#REF! -> #REF! | G15: =SUM(B15:E15)-F15 -> #REF!
A16: 46126 | B16: =SUM(TOTAL!J17:K17) -> 0 | C16: =SUM(#REF!) -> #REF! | D16: =SUM(#REF!) -> #REF! | E16: =SUM(#REF!) -> #REF! | F16: =#REF! -> #REF! | G16: =SUM(B16:E16)-F16 -> #REF!
A17: 46127 | B17: =SUM(TOTAL!J18:K18) -> 0 | C17: =SUM(#REF!) -> #REF! | D17: =SUM(#REF!) -> #REF! | E17: =SUM(#REF!) -> #REF! | F17: =#REF! -> #REF! | G17: =SUM(B17:E17)-F17 -> #REF!
A18: 46128 | B18: =SUM(TOTAL!J19:K19) -> 0 | C18: =SUM(#REF!) -> #REF! | D18: =SUM(#REF!) -> #REF! | E18: =SUM(#REF!) -> #REF! | F18: =#REF! -> #REF! | G18: =SUM(B18:E18)-F18 -> #REF!
A19: 46129 | B19: =SUM(TOTAL!J20:K20) -> 0 | C19: =SUM(#REF!) -> #REF! | D19: =SUM(#REF!) -> #REF! | E19: =SUM(#REF!) -> #REF! | F19: =#REF! -> #REF! | G19: =SUM(B19:E19)-F19 -> #REF!
A20: 46130 | B20: =SUM(TOTAL!J21:K21) -> 0 | C20: =SUM(#REF!) -> #REF! | D20: =SUM(#REF!) -> #REF! | E20: =SUM(#REF!) -> #REF! | F20: =#REF! -> #REF! | G20: =SUM(B20:E20)-F20 -> #REF!
A21: 46131 | B21: =SUM(TOTAL!J22:K22) -> 0 | C21: =SUM(#REF!) -> #REF! | D21: =SUM(#REF!) -> #REF! | E21: =SUM(#REF!) -> #REF! | F21: =#REF! -> #REF! | G21: =SUM(B21:E21)-F21 -> #REF!
A22: 46132 | B22: =SUM(TOTAL!J23:K23) -> 0 | C22: =SUM(#REF!) -> #REF! | D22: =SUM(#REF!) -> #REF! | E22: =SUM(#REF!) -> #REF! | F22: =#REF! -> #REF! | G22: =SUM(B22:E22)-F22 -> #REF!
A23: 46133 | B23: =SUM(TOTAL!J24:K24) -> 0 | C23: =SUM(#REF!) -> #REF! | D23: =SUM(#REF!) -> #REF! | E23: =SUM(#REF!) -> #REF! | F23: =#REF! -> #REF! | G23: =SUM(B23:E23)-F23 -> #REF!
... A29: 46139 | B29: =SUM(TOTAL!J30:K30) -> 0 | C29: =SUM(#REF!) -> #REF! | D29: =SUM(#REF!) -> #REF! | E29: =SUM(#REF!) -> #REF! | F29: =#REF! -> #REF! | G29: =SUM(B29:E29)-F29 -> #REF!
A30: 46140 | B30: =SUM(TOTAL!#REF!) -> #REF! | C30: =SUM(#REF!) -> #REF! | D30: =SUM(#REF!) -> #REF! | E30: =SUM(#REF!) -> #REF! | F30: =#REF! -> #REF! | G30: =SUM(B30:E30)-F30 -> #REF!

Sheet TOTAL 2
C2: ventesurplace | H2: ventelivraison
B4: date | C4: esp | D4: chq | E4: cb | F4: depense | H4: esp | I4: chq | J4: cb | K4: virement | N4: TOTALESPECES
B5: 46113 | C5: =#REF! -> #REF! | D5: =#REF! -> #REF! | E5: =#REF! -> #REF! | F5: =#REF! -> #REF! | H5: =VLOOKUP($N$4,#REF!,4,FALSE) -> #REF! | I5: =VLOOKUP($N$5,#REF!,4,FALSE) -> #REF! | J5: =VLOOKUP($N$6,#REF!,4,FALSE) -> #REF! | K5: {=#REF!} -> #REF! | N5: TOTALCHEQUES
B6: 46116 | C6: ='2'!$C$14 -> 5630 | D6: ='2'!$E$15 -> 2013.78 | E6: ='2'!$G$15 -> 24011.5 | F6: ='2'!$L$16 -> -173 | H6: =VLOOKUP($N$4,'2'!B:L,4,FALSE) -> 1543.88 | I6: =VLOOKUP($N$5,'2'!B:L,4,FALSE) -> 7410.31 | J6: =VLOOKUP($N$6,'2'!B:L,4,FALSE) -> 17281.26 | K6: {='2'!$K$7:$L$7} -> 0 | L6: 0 | N6: TOTALCBInternet&Phone
B7: 46116 | C7: ='3'!$C$14 -> 9510 | D7: ='3'!$E$15 -> 1450.56 | E7: ='3'!$G$15 -> 10834.72 | F7: ='3'!$L$16 -> 206 | H7: =VLOOKUP($N$4,'3'!B:L,4,FALSE) -> 639.46 | I7: =VLOOKUP($N$5,'3'!B:L,4,FALSE) -> 1300.58 | J7: =VLOOKUP($N$6,'3'!B:L,4,FALSE) -> 26674.64 | K7: {='3'!$K$7:$L$7} -> 0 | L7: 0
B8: 46116 | C8: ='4'!$C$14 -> 13470 | D8: ='4'!$E$15 -> 1608.59 | E8: ='4'!$G$15 -> 25778.66 | F8: ='4'!$L$16 -> -1006 | H8: =VLOOKUP($N$4,'4'!B:L,4,FALSE) -> 0 | I8: =VLOOKUP($N$5,'4'!B:L,4,FALSE) -> 0 | J8: =VLOOKUP($N$6,'4'!B:L,4,FALSE) -> 0 | K8: {='4'!$K$7:$L$7} -> 0 | L8: 0
B9: 46117 | C9: ='5'!$C$14 -> 0 | D9: ='5'!$E$15 -> 0 | E9: ='5'!$G$15 -> 0 | F9: ='5'!$L$16 -> 596 | H9: =VLOOKUP($N$4,'5'!B:L,4,FALSE) -> 0 | I9: =VLOOKUP($N$5,'5'!B:L,4,FALSE) -> 0 | J9: =VLOOKUP($N$6,'5'!B:L,4,FALSE) -> 0 | K9: {='5'!$K$7:$L$7} -> 0 | L9: 0
B10: 46118 | C10: ='6'!$C$14 -> 10440 | D10: ='6'!$E$15 -> 1400.18 | E10: ='6'!$G$15 -> 22371.77 | F10: ='6'!$L$16 -> -656.5 | H10: =VLOOKUP($N$4,'6'!B:L,4,FALSE) -> 0 | I10: =VLOOKUP($N$5,'6'!B:L,4,FALSE) -> 0 | J10: =VLOOKUP($N$6,'6'!B:L,4,FALSE) -> 0 | K10: {='6'!$K$7:$L$7} -> 0 | L10: 0
B11: 46119 | C11: ='7'!$C$14 -> 6200 | D11: ='7'!$E$15 -> 3797.44 | E11: ='7'!$G$15 -> 26103.54 | F11: ='7'!$L$16 -> -902.85 | H11: =VLOOKUP($N$4,'7'!B:L,4,FALSE) -> 1076.35 | I11: =VLOOKUP($N$5,'7'!B:L,4,FALSE) -> 9794.85 | J11: =VLOOKUP($N$6,'7'!B:L,4,FALSE) -> 1172.44 | K11: {='7'!$K$7:$L$7} -> 18382.79 | L11: 0
B12: 46120 | C12: =#REF! -> #REF! | D12: =#REF! -> #REF! | E12: =#REF! -> #REF! | F12: =#REF! -> #REF! | H12: =VLOOKUP($N$4,#REF!,4,FALSE) -> #REF! | I12: =VLOOKUP($N$5,#REF!,4,FALSE) -> #REF! | J12: =VLOOKUP($N$6,#REF!,4,FALSE) -> #REF! | K12: {=#REF!} -> #REF!
B13: 46121 | C13: ='8'!$C$14 -> 8715 | D13: ='8'!$E$15 -> 1235.5 | E13: ='8'!$G$15 -> 24660.95 | F13: ='8'!$L$16*-1 -> 413.6 | H13: =VLOOKUP($N$4,'8'!B:L,4,FALSE) -> 1491.6 | I13: =VLOOKUP($N$5,'8'!B:L,4,FALSE) -> 3537.35 | J13: =VLOOKUP($N$6,'8'!B:L,4,FALSE) -> 0 | K13: {='8'!$K$7:$L$7} -> 0 | L13: 0
B14: 46122 | C14: ='10'!$C$14 -> 6240 | D14: ='10'!$E$15 -> 309.49 | E14: ='10'!$G$15 -> 15955.55 | F14: ='10'!$L$16 -> -192 | H14: =VLOOKUP($N$4,'10'!B:L,4,FALSE) -> 477.7 | I14: =VLOOKUP($N$5,'10'!B:L,4,FALSE) -> 6413.88 | J14: =VLOOKUP($N$6,'10'!B:L,4,FALSE) -> 10182.48 | K14: {='10'!$K$7:$L$7} -> 0 | L14: 0
B15: 46123 | C15: ='[2]04'!$C$14 -> #REF! | D15: ='11'!$E$15 -> 1582.95 | E15: ='11'!$G$15 -> 22365.06 | F15: ='11'!$L$16 -> -472 | H15: =VLOOKUP($N$4,'11'!B:L,4,FALSE) -> 0 | I15: =VLOOKUP($N$5,'11'!B:L,4,FALSE) -> 0 | J15: =VLOOKUP($N$6,'11'!B:L,4,FALSE) -> 0 | K15: {='11'!$K$7:$L$7} -> 0 | L15: 0
B16: 46065 | C16: =#REF! -> #REF! | D16: =#REF! -> #REF! | E16: =#REF! -> #REF! | F16: =#REF! -> #REF! | H16: =VLOOKUP($N$4,#REF!,4,FALSE) -> #REF! | I16: =VLOOKUP($N$5,#REF!,4,FALSE) -> #REF! | J16: =VLOOKUP($N$6,#REF!,4,FALSE) -> #REF! | K16: {=#REF!} -> #REF!
B17: 46066 | C17: ='13'!$C$15 -> 374 | D17: ='13'!$E$16 -> 0 | E17: ='13'!$G$16 -> 0 | F17: ='13'!$L$17 -> 0 | H17: =VLOOKUP($N$4,'13'!B:L,4,FALSE) -> 1734.22 | I17: =VLOOKUP($N$5,'13'!B:L,4,FALSE) -> 4054.54 | J17: =VLOOKUP($N$6,'13'!B:L,4,FALSE) -> 0 | K17: {='13'!$K$7:$L$7} -> 293540.43 | L17: 0
B18: 46067 | C18: ='14'!$C$17 -> 10080 | D18: ='14'!$E$18 -> 275.87 | E18: ='14'!$G$18 -> 18118.33 | F18: ='14'!$L$19 -> -1804 | H18: =VLOOKUP($N$4,'14'!B:L,4,FALSE) -> 94.53 | I18: =VLOOKUP($N$5,'14'!B:L,4,FALSE) -> 2048.14 | J18: =VLOOKUP($N$6,'14'!B:L,4,FALSE) -> 0 | K18: {='14'!$K$7:$L$7} -> 244293.16 | L18: 0
B19: 46068 | C19: =#REF! -> #REF! | D19: =#REF! -> #REF! | E19: =#REF! -> #REF! | F19: =#REF! -> #REF! | H19: =VLOOKUP($N$4,#REF!,4,FALSE) -> #REF! | I19: =VLOOKUP($N$5,#REF!,4,FALSE) -> #REF! | J19: =VLOOKUP($N$6,#REF!,4,FALSE) -> #REF! | K19: {=#REF!} -> #REF!
B20: 46069 | C20: ='15'!$C$14 -> 5520 | D20: ='15'!$E$15 -> 1094.48 | E20: ='15'!$G$15 -> 19899.16 | F20: ='15'!$L$16*-1 -> -37.2 | H20: =VLOOKUP($N$4,'15'!B:L,4,FALSE) -> 1385.92 | I20: =VLOOKUP($N$5,'15'!B:L,4,FALSE) -> 3371.73 | J20: =VLOOKUP($N$6,'15'!B:L,4,FALSE) -> 44636.8 | K20: {='15'!$K$7:$L$7} -> 354933.52 | L20: 0
B21: 46070 | C21: ='17'!$C$14 -> 3725 | D21: ='17'!$E$15 -> 559.87 | E21: ='17'!$G$15 -> 16803.8 | F21: ='17'!$L$16 -> -1191 | H21: =VLOOKUP($N$4,'17'!B:L,4,FALSE) -> 9.24 | I21: =VLOOKUP($N$5,'17'!B:L,4,FALSE) -> 13513.4 | J21: =VLOOKUP($N$6,'17'!B:L,4,FALSE) -> 0 | K21: {='17'!$K$7:$L$7} -> 0 | L21: 0
B22: 46071 | C22: ='18'!$C$17 -> 0 | D22: ='18'!$E$18 -> 0 | E22: ='18'!$G$18 -> 0 | F22: ='18'!$L$19 -> SAP | H22: =VLOOKUP($N$4,'18'!B:L,4,FALSE) -> 0 | I22: =VLOOKUP($N$5,'18'!B:L,4,FALSE) -> 0 | J22: =VLOOKUP($N$6,'18'!B:L,4,FALSE) -> 0 | K22: {='18'!$K$7:$L$7} -> 0 | L22: 0
B23: 46072 | C23: ='19'!$C$14 -> 0 | D23: ='19'!$E$15 -> 0 | E23: ='19'!$G$15 -> 0 | F23: ='19'!$L$16 -> 253 | H23: =VLOOKUP($N$4,'19'!B:L,4,FALSE) -> 0 | I23: =VLOOKUP($N$5,'19'!B:L,4,FALSE) -> 0 | J23: =VLOOKUP($N$6,'19'!B:L,4,FALSE) -> 0 | K23: {='19'!$K$7:$L$7} -> 0 | L23: 0
B24: 46073 | C24: ='20'!$C$15 -> 7275 | D24: ='20'!$E$16 -> 1558.08 | E24: ='20'!$G$16 -> 19916.27 | F24: ='20'!$L$17 -> -1546 | H24: =VLOOKUP($N$4,'20'!B:L,4,FALSE) -> 2980.75 | I24: =VLOOKUP($N$5,'20'!B:L,4,FALSE) -> 2575.22 | J24: =VLOOKUP($N$6,'20'!B:L,4,FALSE) -> 6151.93 | K24: {='20'!$K$7:$L$7} -> 269425.29 | L24: 0
B25: 46074 | C25: ='21'!$C$17 -> 5805 | D25: ='21'!$E$18 -> 674.08 | E25: ='21'!$G$18 -> 23821.13 | F25: ='21'!$L$19*-1 -> 903 | H25: =VLOOKUP($N$4,'21'!B:L,4,FALSE) -> 50 | I25: =VLOOKUP($N$5,'21'!B:L,4,FALSE) -> 4025.33 | J25: =VLOOKUP($N$6,'21'!B:L,4,FALSE) -> 9360.43 | K25: {='21'!$K$7:$L$7} -> 0 | L25: 0
B26: 46075 | C26: =#REF! -> #REF! | D26: =#REF! -> #REF! | E26: =#REF! -> #REF! | F26: =#REF! -> #REF! | H26: =VLOOKUP($N$4,#REF!,4,FALSE) -> #REF! | I26: =VLOOKUP($N$5,#REF!,4,FALSE) -> #REF! | J26: =VLOOKUP($N$6,#REF!,4,FALSE) -> #REF! | K26: {=#REF!} -> #REF!
B27: 46076 | C27: ='23'!$C$14 -> 6240 | D27: ='23'!$E$15 -> 260.52 | E27: ='23'!$G$15 -> 17024.65 | F27: ='23'!$L$16*-1 -> 633 | H27: =VLOOKUP($N$4,'23'!B:L,4,FALSE) -> 1630.34 | I27: =VLOOKUP($N$5,'23'!B:L,4,FALSE) -> 4013.64 | J27: =VLOOKUP($N$6,'23'!B:L,4,FALSE) -> 20621.8 | K27: {='23'!$K$7:$L$7} -> 0 | L27: 0
B28: 46077 | C28: ='24'!$C$14 -> 4850 | D28: ='24'!$E$15 -> 1472.08 | E28: ='24'!$G$15 -> 18456.89 | F28: ='24'!$L$16 -> -173 | H28: =VLOOKUP($N$4,'24'!B:L,4,FALSE) -> 2643.09 | I28: =VLOOKUP($N$5,'24'!B:L,4,FALSE) -> 3104.06 | J28: =VLOOKUP($N$6,'24'!B:L,4,FALSE) -> 2188.52 | K28: {='24'!$K$7:$L$7} -> 0 | L28: 0
B29: 46078 | C29: ='25'!$C$14 -> 11910 | D29: ='25'!$E$15 -> 1383.68 | E29: ='25'!$G$15 -> 26970.91 | F29: ='25'!$L$16 -> 32 | H29: =VLOOKUP($N$4,'25'!B:L,4,FALSE) -> 46.75 | I29: =VLOOKUP($N$5,'25'!B:L,4,FALSE) -> 0 | J29: =VLOOKUP($N$6,'25'!B:L,4,FALSE) -> 0 | K29: {='25'!$K$7:$L$7} -> 0 | L29: 0
B30: 46079 | C30: ='26'!$C$14 -> 0 | D30: ='26'!$E$15 -> 0 | E30: ='26'!$G$15 -> 0 | F30: ='26'!$L$16 -> 241 | H30: =VLOOKUP($N$4,'26'!B:L,4,FALSE) -> 0 | I30: =VLOOKUP($N$5,'26'!B:L,4,FALSE) -> 0 | J30: =VLOOKUP($N$6,'26'!B:L,4,FALSE) -> 0 | K30: {='26'!$K$7:$L$7} -> 0 | L30: 0
B31: 46080 | C31: ='27'!$C$14 -> 7780 | D31: ='27'!$E$15 -> 2459.86 | E31: ='27'!$G$15 -> 19873.58 | F31: ='27'!$L$16 -> -1210 | H31: =VLOOKUP($N$4,'27'!B:L,4,FALSE) -> 61.56 | I31: =VLOOKUP($N$5,'27'!B:L,4,FALSE) -> 3234.64 | J31: =VLOOKUP($N$6,'27'!B:L,4,FALSE) -> 3587.95 | K31: {='27'!$K$7:$L$7} -> 0 | L31: 0
B32: 46081 | C32: ='28'!$C$14 -> 3580 | D32: ='28'!$E$15 -> 3606.03 | E32: ='28'!$G$15 -> 18206.48 | F32: ='28'!$L$16 -> -322.8 | H32: =VLOOKUP($N$4,'28'!B:L,4,FALSE) -> 11617.42 | I32: =VLOOKUP($N$5,'28'!B:L,4,FALSE) -> 3825.55 | J32: =VLOOKUP($N$6,'28'!B:L,4,FALSE) -> 5820.11 | K32: {='28'!$K$7:$L$7} -> 251048.82 | L32: 0
